{
  "dc_identifier_s": "4383ac33-4fbb-42f3-96d3-f8915283f9e2",
  "dc_title_s": "County & township map of the states of Ohio and Indiana.",
  "dc_description_s": "Prime meridian: Washington.; Detached from an atlas, no. 68. Scale approximately 1:1,300,000.",
  "dc_rights_s": "Public",
  "dc_format_s": "JPEG",
  "dc_language_sm": [
    "English"
  ],
  "dc_type_sm": [
    "Image"
  ],
  "dc_publisher_sm": [
    "S. Augustus Mitchell"
  ],
  "dc_creator_sm": [
    "Mitchell,  S. Augustus(Samuel Augustus), 1792-1868, cartographer."
  ],
  "dc_subject_sm": [

  ],
  "dct_provenance_s": "Indiana",
  "dct_references_s": "{\"http://schema.org/url\":\"http://purl.dlib.indiana.edu/iudl/images/VAC3073/VAC3073-M-00402\",\"http://schema.org/downloadUrl\":\"https://purl.dlib.indiana.edu/iudl/images/VAC3073/full/VAC3073-M-00402\"}",
  "dct_isPartOf_sm": [
    "Indiana Historic Maps"
  ],
  "dct_issued_s": "",
  "dct_temporal_sm": [
    "1877"
  ],
  "dct_spatial_sm": [
    "Ohio, United States",
    "Indiana, United States"
  ],
  "layer_slug_s": "4383ac33-4fbb-42f3-96d3-f8915283f9e2",
  "layer_geom_type_s": "Image",
  "layer_modified_dt": "2018-07-09T20:12:13Z",
  "solr_geom": "ENVELOPE(-88.08, -80.6, 41.75, 37.9)",
  "solr_year_i": 1877,
  "b1g_genre_sm": [
    "Maps"
  ],
  "b1g_centroid_ss": "39.825,-84.34",
  "b1g_geonames_sm": [
    "http://sws.geonames.org/5165418",
    "http://sws.geonames.org/4921868"
  ],
  "b1g_image_ss": "https://purl.dlib.indiana.edu/iudl/images/VAC3073/thumbnail/VAC3073-M-00402",
  "b1g_collection_sm": "01d-01",
  "geoblacklight_version": "1.0"
}