{
  "dc_identifier_s": "8f50e0f3-65b6-4e5e-8747-90aab925acf7",
  "dc_title_s": "A map of the British and French settlements in North America; J. Lodge, delin. et sculp.",
  "dc_description_s": "Covers the eastern half of North America from Hudson Bay to the Gulf of Mexico. Relief shown pictorially. Shows boundaries, cities and towns, forts, Indian villages and tribal territory, and \"Earl Granville's Property.\" \"Longitude w. from London.\" \"The French Incroachments are shewn by Oblique strokes, and their Forts with two Strokes, the English Forts by a single Stroke.\" Includes a brief historical note on the English claim to North America and the origins of several colonies. Appeared in Gentleman's Magazine in July, 1755. 1 map; 28 x 39 cm., folded to 18 x 10 cm. This map is in the public domain. Please attribute access and use of this digitized map to the Stephen S. Clark Library, University of Michigan Library.",
  "dc_rights_s": "Public",
  "dc_format_s": "JPEG",
  "dc_language_sm": [
    "English"
  ],
  "dc_type_sm": [
    "Image"
  ],
  "dc_publisher_sm": [

  ],
  "dc_creator_sm": [
    "Lodge, John, -1796.,Dahl, James, former owner."
  ],
  "dc_subject_sm": [

  ],
  "dct_provenance_s": "Michigan",
  "dct_references_s": "{\"http://schema.org/url\":\"https://quod.lib.umich.edu/c/clark1ic/x-003566121/39015095390566\",\"http://schema.org/downloadUrl\":\"https://quod.lib.umich.edu/cgi/i/image/api/image/clark1ic:003566121:39015095390566/full/res:1/0/native.jpg?attachment=1\",\"http://iiif.io/api/image\":\"https://quod.lib.umich.edu/cgi/i/image/api/image/clark1ic:003566121:39015095390566/info.json\"}",
  "dct_isPartOf_sm": [
    "Clark Library Map Collections"
  ],
  "dct_issued_s": "",
  "dct_temporal_sm": [
    "1755?"
  ],
  "dct_spatial_sm": [
    "Northern America"
  ],
  "layer_slug_s": "8f50e0f3-65b6-4e5e-8747-90aab925acf7",
  "layer_geom_type_s": "Image",
  "layer_modified_dt": "2018-07-05T21:55:57Z",
  "solr_geom": "ENVELOPE(-96.88, -51.68, 52.57, 28.85)",
  "solr_year_i": 1755,
  "b1g_genre_sm": [
    "Maps"
  ],
  "b1g_centroid_ss": "40.71,-74.28",
  "b1g_geonames_sm": [
    "http://sws.geonames.org/7729890"
  ],
  "b1g_image_ss": "https://quod.lib.umich.edu/cgi/i/image/api/image/clark1ic:003566121:39015095390566/full/res:1/0/native.jpg?attachment=1",
  "b1g_collection_sm": "07d-01",
  "geoblacklight_version": "1.0"
}