{
  "dc_identifier_s": "180f5d69-fecd-49c4-93be-f3d194599dd0",
  "dc_title_s": "Map of Chicago, showing land values, 1892 :average values for square mile and 960 acre tracts in dollars per acre.",
  "dc_description_s": "Scale approximately 1:175,300; Master and use copy. Digital master created according to Benchmark for Faithful Reproductions of Monographs and Serials, Version 1. Digital Library Federation, December 2002.",
  "dc_rights_s": "Public",
  "dc_format_s": "JPEG",
  "dc_language_sm": [
    "English"
  ],
  "dc_type_sm": [
    "Image"
  ],
  "dc_publisher_sm": [

  ],
  "dc_creator_sm": [
    "University of Chicago Social Science Research Committee"
  ],
  "dc_subject_sm": [
    "Real property"
  ],
  "dct_provenance_s": "Chicago",
  "dct_references_s": "{\"http://schema.org/url\":\"https://pi.lib.uchicago.edu/1001/maps/chisoc/G4104-C6-1933-U5-k\",\"http://schema.org/downloadUrl\":\"https://luna.lib.uchicago.edu/MediaManager/srvr?mediafile=/Size4/UCHICAGO~2~2/1718/G4104-C6-1933-U5-k.jpg\"}",
  "dct_isPartOf_sm": [
    "University of Chicago Social Science Maps"
  ],
  "dct_issued_s": "",
  "dct_temporal_sm": [
    "1892"
  ],
  "dct_spatial_sm": [
    "Chicago, Illinois, United States",
    "Illinois, United States"
  ],
  "layer_slug_s": "180f5d69-fecd-49c4-93be-f3d194599dd0",
  "layer_geom_type_s": "Image",
  "layer_modified_dt": "2018-07-09T20:20:26Z",
  "solr_geom": "ENVELOPE(-87.8511, -87.5236, 42.0231, 41.6442)",
  "solr_year_i": 1892,
  "b1g_genre_sm": [
    "Maps"
  ],
  "b1g_centroid_ss": "41.83365,-87.68735",
  "b1g_geonames_sm": [
    "http://sws.geonames.org/4887398"
  ],
  "b1g_image_ss": "https://btaagdp.org/maps/files/original/27835bd36f8e8ac5c5b7a4bff90232ee.jpg",
  "b1g_collection_sm": "12d-01",
  "geoblacklight_version": "1.0"
}