{
  "geoblacklight_version": "1.0",
  "layer_modified_dt": "2020-07-17T22:46:42Z",
  "dc_rights_s": "Public",
  "dc_title_s": "Municipal Wards: Wisconsin, 2020",
  "dct_alternativeTitle_sm": [
    "Municipal Wards, Wisconsin 2020"
  ],
  "dc_description_s": "This data layer represents municipal wards in Wisconsin in the spring of 2020.",
  "dc_language_sm": [
    "English"
  ],
  "dc_creator_sm": [
    "Wisconsin Legislative Technology Services Bureau"
  ],
  "dc_publisher_sm": [
    "State of Wisconsin"
  ],
  "b1g_genre_sm": [
    "Geospatial data"
  ],
  "dc_subject_sm": [
    "Boundaries"
  ],
  "dct_temporal_sm": [
    "2020"
  ],
  "solr_year_i": "2020",
  "dct_spatial_sm": [
    "Wisconsin"
  ],
  "solr_geom": "ENVELOPE(-92.889345, -86.763994, 47.080722, 42.491922)",
  "b1g_centroid_ss": "44.786322,-89.82666950000001",
  "dc_type_sm": [
    "Dataset",
    "Service"
  ],
  "layer_geom_type_s": "Vector",
  "dc_format_s": "Shapefile",
  "layer_slug_s": "7CB244A2-FEDC-4959-8808-BB00BEAE417D",
  "dc_identifier_s": "7CB244A2-FEDC-4959-8808-BB00BEAE417D",
  "dct_provenance_s": "Wisconsin",
  "b1g_code_s": "10a-01",
  "dct_isPartOf_sm": [
    "10a-01"
  ],
  "b1g_status_s": "Active",
  "b1g_dateAccessioned_s": "2020-07-17",
  "suppressed_b": "FALSE",
  "b1g_child_record_b": "FALSE"
}