{
  "dc_identifier_s": "9F8AE702-843F-405E-A20C-2BC172B1CD6D",
  "dc_title_s": "Zoning Washington County, Wisconsin, 2017",
  "dc_description_s": "These polygon data layers represent zoning for Washington County, Wisconsin in 2017. They are feature classes within the geodatabase Washington_Zoning_2017.gdb. The features included in this geodatabase are 'Floodplain' and 'Shoreland'.",
  "dc_rights_s": "Public",
  "dc_format_s": "Geodatabase",
  "dc_language_sm": [
    "English"
  ],
  "dc_type_sm": "Dataset",
  "dc_publisher_sm": [
    "Washington County, Wisconsin"
  ],
  "dc_creator_sm": [
    "Washington County Geographic Information System Division"
  ],
  "dc_subject_sm": [
    "Planning and Cadastral",
    "Zoning"
  ],
  "dct_provenance_s": "Wisconsin",
  "dct_references_s": "{\"http://schema.org/downloadUrl\":\"https://gisdata.wisc.edu/public/Washington_Zoning_2017.zip\",\"http://www.isotc211.org/schemas/2005/gmd/\":\"http://64.90.181.107/geonetwork/srv/api/records/9F8AE702-843F-405E-A20C-2BC172B1CD6D/formatters/xml\"}",
  "dct_isPartOf_sm": [
    "Wisconsin Counties Open Data"
  ],
  "dct_issued_s": "2017-03-24",
  "dct_temporal_sm": [
    "2017"
  ],
  "dct_spatial_sm": [
    "Washington County, Wisconsin, United States",
    "Wisconsin, United States"
  ],
  "layer_slug_s": "9F8AE702-843F-405E-A20C-2BC172B1CD6D",
  "layer_geom_type_s": "Polygon",
  "layer_modified_dt": "2018-06-26T21:10:08Z",
  "solr_geom": "ENVELOPE(-88.422329, -88.035387, 43.547713, 43.188383)",
  "solr_year_i": 2017,
  "b1g_genre_sm": [
    "Geospatial data"
  ],
  "b1g_centroid_ss": "43.368048,-88.228858",
  "b1g_geonames_sm": [
    "http://sws.geonames.org/5279468"
  ],
  "b1g_image_ss": "",
  "b1g_collection_sm": "10b-01",
  "geoblacklight_version": "1.0"
}