{
  "geoblacklight_version": "1.0",
  "layer_modified_dt": "2020-01-17T15:31:30Z",
  "layer_slug_s": "81074259-dda3-41ab-a5ee-b230c7eb2018",
  "dc_identifier_s": "81074259-dda3-41ab-a5ee-b230c7eb2018",
  "dc_title_s": "Minnesota",
  "dct_alternativeTitle_sm": [
    "Minnesota"
  ],
  "dc_description_s": "Atlas plate 49. Longitude west from Greenwich and Washington, D.C. Possibly a map from: Colton\u2019s Atlas of America, 1856, according to an early cataloger\u2019s note. 7 x 6 inches",
  "dc_creator_sm": [
    "Colby, Charles Galusha, 1830-1866?"
  ],
  "dc_publisher_sm": [
    "[s.n.]"
  ],
  "dc_subject_sm": [
    ""
  ],
  "b1g_keyword_sm": [
    "Minnesota Maps"
  ],
  "dc_type_sm": [
    "Image"
  ],
  "b1g_genre_sm": [
    "Maps"
  ],
  "dc_format_s": "JPEG",
  "layer_geom_type_s": "Image",
  "dct_provenance_s": "Minnesota",
  "dct_issued_s": "",
  "dct_temporal_sm": [
    "1857"
  ],
  "b1g_date_range_drsim": [
    ""
  ],
  "solr_year_i": "1857",
  "dct_spatial_sm": [
    "Minnesota"
  ],
  "solr_geom": "ENVELOPE(-96.79573059,-90.37902832,48.75618876,43.42898792)",
  "b1g_centroid_ss": "46.09258834,-93.587379455",
  "dc_language_sm": [
    "English"
  ],
  "b1g_code_s": "05d-01",
  "dct_isPartOf_sm": [
    "05d-p16022coll247,05d-01"
  ],
  "b1g_dateAccessioned_s": "2019-07-26",
  "b1g_dateRetired_s": "",
  "dct_accrualMethod_s": "Blacklight",
  "b1g_status_s": "Active",
  "dc_rights_s": "Public",
  "suppressed_b": "",
  "dct_references_s": "{\"http://schema.org/url\":\"http://purl.umn.edu/89343\",\"http://iiif.io/api/presentation#manifest\":\"https://cdm16022.contentdm.oclc.org/iiif/info/p16022coll247/268/manifest.json\"}",
  "layer_id_s": "268",
  "b1g_image_ss": "https://cdm16022.contentdm.oclc.org/utils/getthumbnail/collection/p16022coll247/id/268"
}