{
  "dc_identifier_s": "0b4f1268-04cd-4bf0-bb52-454147481529",
  "dc_title_s": "Burmah, Siam, and Cochin China",
  "dc_description_s": "Cartographic Details: Scale approximately 1:4,435,200. Map of British possessions, territories under Britsh influence and independent states in Burma, Thailand and Indochina with relief shown by hachures. In top right margin: 31. 1 map : color ; 58.3 x 47 cm",
  "dc_rights_s": "Public",
  "dc_format_s": "TIFF",
  "dc_language_sm": [
    "English"
  ],
  "dc_type_sm": [
    "Image"
  ],
  "dc_publisher_sm": [
    "Pubd. 14 Feby. 1832, by J. Arrowsmith, 35 Essex Street Strand"
  ],
  "dc_creator_sm": [
    "John Arrowsmith 1790-1873."
  ],
  "dc_subject_sm": [

  ],
  "dct_provenance_s": "Minnesota",
  "dct_references_s": "{\"http://schema.org/url\":\"http://purl.umn.edu/229181\",\"http://schema.org/downloadUrl\":\"https://umedia.lib.umn.edu/sites/default/files/archive/419/image/tiff/1087912.tif\",\"http://iiif.io/api/image\":\"https://umedia.lib.umn.edu/fcgi-bin/iipsrv.fcgi?IIIF=sites/default/files/reference/419/image/jp2/1087912.jp2/info.json\"}",
  "dct_isPartOf_sm": [
    "John R. Borchert Map Library"
  ],
  "dct_issued_s": "",
  "dct_temporal_sm": [
    "1832"
  ],
  "dct_spatial_sm": [
    "Thailand",
    "Burma, Myanmar [Burma]"
  ],
  "layer_slug_s": "0b4f1268-04cd-4bf0-bb52-454147481529",
  "layer_geom_type_s": "Image",
  "layer_modified_dt": "2018-07-06T18:49:49Z",
  "solr_geom": "ENVELOPE(89.54956055, 110.4153442, 28.69781552, 5.054694508)",
  "solr_year_i": 1832,
  "b1g_genre_sm": [
    "Maps"
  ],
  "b1g_centroid_ss": "16.876255014,99.982452375",
  "b1g_geonames_sm": [
    "http://sws.geonames.org/1605651",
    "http://sws.geonames.org/1327865"
  ],
  "b1g_image_ss": "https://umedia.lib.umn.edu/sites/default/files/imagecache/square300/reference/419/image/jpeg/1087912.jpg",
  "b1g_collection_sm": "05d-01",
  "geoblacklight_version": "1.0"
}