{
  "geoblacklight_version": "1.0",
  "layer_modified_dt": "2020-01-17T15:41:30Z",
  "layer_slug_s": "d943e4bf-efbc-479d-83f6-78dbac2a981f",
  "dc_identifier_s": "d943e4bf-efbc-479d-83f6-78dbac2a981f",
  "dc_title_s": "3325 M.S. Fragment of contemporary Spanish map with inscription relating to the Magellan Expedition.",
  "dct_alternativeTitle_sm": [
    ""
  ],
  "dc_description_s": "Magalh\u00e3es, Fern\u00e3o de, -1521--Maps--Facsimiles.",
  "dc_creator_sm": [
    ""
  ],
  "dc_publisher_sm": [
    ""
  ],
  "dc_subject_sm": [
    ""
  ],
  "b1g_keyword_sm": [
    "Penn State Rare Maps"
  ],
  "dc_type_sm": [
    "Image"
  ],
  "b1g_genre_sm": [
    "Maps"
  ],
  "dc_format_s": "JPEG",
  "layer_geom_type_s": "Image",
  "dct_provenance_s": "Penn State",
  "dct_issued_s": "",
  "dct_temporal_sm": [
    "1521"
  ],
  "b1g_date_range_drsim": [
    "[1521 TO 1521]"
  ],
  "solr_year_i": "1521",
  "dct_spatial_sm": [
    "Africa",
    "Asia"
  ],
  "solr_geom": "ENVELOPE(42.35,75.58333333,40.76666667,9.866666667)",
  "b1g_centroid_ss": "25.316666668499998,58.966666665000005",
  "dc_language_sm": [
    "English"
  ],
  "b1g_code_s": "08d-01",
  "dct_isPartOf_sm": [
    "08d-01"
  ],
  "b1g_dateAccessioned_s": "2019-01-16",
  "b1g_dateRetired_s": "",
  "dct_accrualMethod_s": "",
  "b1g_status_s": "Active",
  "dc_rights_s": "Public",
  "suppressed_b": "FALSE",
  "dct_references_s": "{\"http://iiif.io/api/presentation#manifest\":\"https://digital.libraries.psu.edu/iiif/info/maps1/30183/manifest.json\",\"http://schema.org/url\":\"https://collection1.libraries.psu.edu/cdm/ref/collection/maps1/id/30183\"}",
  "layer_id_s": "",
  "b1g_image_ss": ""
}