{
  "geoblacklight_version": "1.0",
  "layer_modified_dt": "2020-03-09T20:27:38Z",
  "dc_rights_s": "Public",
  "layer_slug_s": "09ab43f49792492dbc3ab5788f98273c_20",
  "dc_identifier_s": "09ab43f49792492dbc3ab5788f98273c_20",
  "b1g_code_s": "01c-02",
  "dct_isPartOf_sm": [
    "01c-02"
  ],
  "b1g_dateAccessioned_s": "2020-03-06",
  "b1g_status_s": "Active",
  "suppressed_b": "FALSE",
  "dct_accrualMethod_s": "ArcGIS Hub",
  "dc_title_s": "Bike ways and Green ways: City of Indianapolis and Marion County, Indiana",
  "dct_alternativeTitle_sm": [
    "Bike ways and Green ways"
  ],
  "dc_description_s": "Line file representing Bike ways and Green ways in Indianapolis and Marion County, Indiana.Data projection: NAD 1983 StatePlane Indiana East FIPS 1301 (US Feet)",
  "b1g_genre_sm": [
    "Geospatial data"
  ],
  "dc_subject_sm": [
    "Transportation"
  ],
  "b1g_keyword_sm": [
    "Transportation",
    "Bikeways and Greenways",
    "Indianapolis"
  ],
  "dc_format_s": "Shapefile",
  "dc_type_sm": [
    "Dataset",
    "Service"
  ],
  "layer_geom_type_s": "Vector",
  "dct_issued_s": "2020-02-20T15:08:51.000Z",
  "dct_temporal_sm": [
    "2020"
  ],
  "solr_year_i": "2020",
  "b1g_date_range_drsim": [
    "[2020 TO 2020]"
  ],
  "dct_spatial_sm": [
    "Indianapolis, Marion County, Indiana",
    "Marion County, Indiana",
    "Indiana"
  ],
  "solr_geom": "ENVELOPE(-86.3415,-85.9382,39.9312,39.6332)",
  "b1g_centroid_ss": "39.7822,-86.13985",
  "dct_provenance_s": "Indiana",
  "dc_publisher_sm": [
    "City of Indianapolis and Marion County, Indiana"
  ],
  "dc_creator_sm": [
    "City of Indianapolis and Marion County - IndyGIS"
  ],
  "dc_language_sm": [
    "English"
  ],
  "dct_references_s": "{\"http://schema.org/url\":\"http://data.indy.gov/datasets/09ab43f49792492dbc3ab5788f98273c_20\",\"http://schema.org/downloadUrl\":\"http://data.indy.gov/datasets/09ab43f49792492dbc3ab5788f98273c_20.zip\",\"urn:x-esri:serviceType:ArcGIS#DynamicMapLayer\":\"https://xmaps.indy.gov/arcgis/rest/services/OpenData/OpenData_Transportation/MapServer/20\"}"
}