<gmd:MD_Metadata xmlns:gmd="http://www.isotc211.org/2005/gmd" xmlns:geonet="http://www.fao.org/geonetwork" xmlns:csw="http://www.opengis.net/cat/csw/2.0.2">
    <gmd:fileIdentifier>
      <gco:CharacterString xmlns:gco="http://www.isotc211.org/2005/gco">bb45fca3-c66f-4400-a29a-b0989d34737c</gco:CharacterString>
    </gmd:fileIdentifier>
    <gmd:language>
      <gmd:LanguageCode codeList="http://www.loc.gov/standards/iso639-2/" codeListValue="eng" codeSpace="ISO639-2"/>
    </gmd:language>
    <gmd:characterSet>
      <gmd:MD_CharacterSetCode codeList="http://standards.iso.org/ittf/PubliclyAvailableStandards/ISO_19139_Schemas/resources/codelist/ML_gmxCodelists.xml#MD_CharacterSetCode" codeListValue="utf8" codeSpace="ISOTC211/19115"/>
    </gmd:characterSet>
    <gmd:hierarchyLevel>
      <gmd:MD_ScopeCode codeList="http://standards.iso.org/ittf/PubliclyAvailableStandards/ISO_19139_Schemas/resources/codelist/ML_gmxCodelists.xml#MD_ScopeCode" codeListValue="dataset" codeSpace="ISOTC211/19115"/>
    </gmd:hierarchyLevel>
    <gmd:hierarchyLevelName>
      <gco:CharacterString xmlns:gco="http://www.isotc211.org/2005/gco">dataset</gco:CharacterString>
    </gmd:hierarchyLevelName>
    <gmd:contact>
      <gmd:CI_ResponsibleParty>
        <gmd:contactInfo>
          <gmd:CI_Contact>
            <gmd:contactInstructions>
              <gco:CharacterString xmlns:gco="http://www.isotc211.org/2005/gco">Please refer to the Distribution Information section.</gco:CharacterString>
            </gmd:contactInstructions>
          </gmd:CI_Contact>
        </gmd:contactInfo>
        <gmd:role>
          <gmd:CI_RoleCode codeList="http://standards.iso.org/ittf/PubliclyAvailableStandards/ISO_19139_Schemas/resources/codelist/ML_gmxCodelists.xml#CI_RoleCode" codeListValue="pointOfContact" codeSpace="ISOTC211/19115"/>
        </gmd:role>
      </gmd:CI_ResponsibleParty>
    </gmd:contact>
    <gmd:dateStamp>
      <gco:DateTime xmlns:gco="http://www.isotc211.org/2005/gco">2017-12-22T17:36:35</gco:DateTime>
    </gmd:dateStamp>
    <gmd:metadataStandardName>
      <gco:CharacterString xmlns:gco="http://www.isotc211.org/2005/gco">ISO 19139 Geographic Information - Metadata - Implementation Specification</gco:CharacterString>
    </gmd:metadataStandardName>
    <gmd:metadataStandardVersion>
      <gco:CharacterString xmlns:gco="http://www.isotc211.org/2005/gco">2007</gco:CharacterString>
    </gmd:metadataStandardVersion>
    <gmd:dataSetURI>
      <gco:CharacterString xmlns:gco="http://www.isotc211.org/2005/gco">IL_GNIS_2006_Pt_arc</gco:CharacterString>
    </gmd:dataSetURI>
    <gmd:spatialRepresentationInfo>
      <gmd:MD_VectorSpatialRepresentation>
        <gmd:geometricObjects>
          <gmd:MD_GeometricObjects>
            <gmd:geometricObjectType>
              <gmd:MD_GeometricObjectTypeCode codeList="http://standards.iso.org/ittf/PubliclyAvailableStandards/ISO_19139_Schemas/resources/codelist/ML_gmxCodelists.xml#MD_GeometricObjectTypeCode" codeListValue="point" codeSpace="ISOTC211/19115"/>
            </gmd:geometricObjectType>
            <gmd:geometricObjectCount>
              <gco:Integer xmlns:gco="http://www.isotc211.org/2005/gco">56363</gco:Integer>
            </gmd:geometricObjectCount>
          </gmd:MD_GeometricObjects>
        </gmd:geometricObjects>
      </gmd:MD_VectorSpatialRepresentation>
    </gmd:spatialRepresentationInfo>
    <gmd:identificationInfo>
      <gmd:MD_DataIdentification>
        <gmd:citation>
          <gmd:CI_Citation>
            <gmd:title>
              <gco:CharacterString xmlns:gco="http://www.isotc211.org/2005/gco">U.S. Geographic Names Information System (GNIS): Illinois Portion, 2006</gco:CharacterString>
            </gmd:title>
            <gmd:date>
              <gmd:CI_Date>
                <gmd:date>
                  <gco:Date xmlns:gco="http://www.isotc211.org/2005/gco">1981-05-01</gco:Date>
                </gmd:date>
                <gmd:dateType>
                  <gmd:CI_DateTypeCode codeList="http://standards.iso.org/ittf/PubliclyAvailableStandards/ISO_19139_Schemas/resources/codelist/ML_gmxCodelists.xml#CI_DateTypeCode" codeListValue="publication" codeSpace="ISOTC211/19115"/>
                </gmd:dateType>
              </gmd:CI_Date>
            </gmd:date>
            <gmd:edition>
              <gco:CharacterString xmlns:gco="http://www.isotc211.org/2005/gco">20060824</gco:CharacterString>
            </gmd:edition>
            <gmd:identifier>
              <gmd:MD_Identifier>
                <gmd:code>
                  <gco:CharacterString xmlns:gco="http://www.isotc211.org/2005/gco">urn-bb45fca3-c66f-4400-a29a-b0989d34737c</gco:CharacterString>
                </gmd:code>
              </gmd:MD_Identifier>
            </gmd:identifier>
            <gmd:citedResponsibleParty>
              <gmd:CI_ResponsibleParty>
                <gmd:organisationName>
                  <gco:CharacterString xmlns:gco="http://www.isotc211.org/2005/gco">U.S. Geological Survey</gco:CharacterString>
                </gmd:organisationName>
                <gmd:contactInfo>
                  <gmd:CI_Contact>
                    <gmd:address>
                      <gmd:CI_Address>
                        <gmd:deliveryPoint>
                          <gco:CharacterString xmlns:gco="http://www.isotc211.org/2005/gco">Reston, VA</gco:CharacterString>
                        </gmd:deliveryPoint>
                      </gmd:CI_Address>
                    </gmd:address>
                  </gmd:CI_Contact>
                </gmd:contactInfo>
                <gmd:role>
                  <gmd:CI_RoleCode codeList="http://standards.iso.org/ittf/PubliclyAvailableStandards/ISO_19139_Schemas/resources/codelist/ML_gmxCodelists.xml#CI_RoleCode" codeListValue="publisher" codeSpace="ISOTC211/19115"/>
                </gmd:role>
              </gmd:CI_ResponsibleParty>
            </gmd:citedResponsibleParty>
            <gmd:citedResponsibleParty>
              <gmd:CI_ResponsibleParty>
                <gmd:organisationName>
                  <gco:CharacterString xmlns:gco="http://www.isotc211.org/2005/gco">U.S. Geological Survey</gco:CharacterString>
                </gmd:organisationName>
                <gmd:role>
                  <gmd:CI_RoleCode codeList="http://standards.iso.org/ittf/PubliclyAvailableStandards/ISO_19139_Schemas/resources/codelist/ML_gmxCodelists.xml#CI_RoleCode" codeListValue="originator" codeSpace="ISOTC211/19115"/>
                </gmd:role>
              </gmd:CI_ResponsibleParty>
            </gmd:citedResponsibleParty>
            <gmd:presentationForm>
              <gmd:CI_PresentationFormCode codeList="http://standards.iso.org/ittf/PubliclyAvailableStandards/ISO_19139_Schemas/resources/codelist/ML_gmxCodelists.xml#CI_PresentationFormCode" codeListValue="mapDigital" codeSpace="ISOTC211/19115"/>
            </gmd:presentationForm>
            <gmd:series>
              <gmd:CI_Series>
                <gmd:name>
                  <gco:CharacterString xmlns:gco="http://www.isotc211.org/2005/gco">ISGS GIS Database</gco:CharacterString>
                </gmd:name>
                <gmd:issueIdentification>
                  <gco:CharacterString xmlns:gco="http://www.isotc211.org/2005/gco">GISDB.IL_GNIS_2006_Pt</gco:CharacterString>
                </gmd:issueIdentification>
              </gmd:CI_Series>
            </gmd:series>
            <gmd:collectiveTitle>
              <gco:CharacterString xmlns:gco="http://www.isotc211.org/2005/gco">Illinois Geospatial Data Clearinghouse</gco:CharacterString>
            </gmd:collectiveTitle>
            <gmd:otherCitationDetails>
              <gco:CharacterString xmlns:gco="http://www.isotc211.org/2005/gco">Point</gco:CharacterString>
            </gmd:otherCitationDetails>
          </gmd:CI_Citation>
        </gmd:citation>
        <gmd:abstract>
          <gco:CharacterString xmlns:gco="http://www.isotc211.org/2005/gco">This metadata document is abstracted from the GNIS metadata provided with the original data, with some ISGS-specific information added. The original source for these data is http://geonames.usgs.gov. The ISGS makes them available as a convenience for Illinois data users. This is a point feature class of named places and features in Illinois. It includes place name, location, and general feature type. There are many general feature types, for example, Populated Place, Hospital, Post Office, Reservoir, Airport, Cemetery, and School. Refer to the Overview Description of the Entity and Attributes section for a complete list. The spatial reference is the Geographic Coordinate system (longitude and latitude). The GNIS metadata fails to specify a datum for the longitude/latitude values. This is not significant because the locations are extremely generalized. However, to make the data work in ArcGIS, the ISGS arbitrarily assigned the NAD83 datum to the data. The Geographic Names Information System (GNIS) is the Federal standard for geographic nomenclature. The U.S. Geological Survey developed the GNIS for the U.S. Board on Geographic Names, a Federal inter-agency body chartered by public law to maintain uniform feature name usage throughout the Government and to promulgate standard names to the public. The GNIS is the official repository of domestic geographic names data; the official vehicle for geographic names use by all departments of the Federal Government; and the source for applying geographic names to Federal electronic and printed products of all types. See http://geonames.usgs.gov for additional information. The original metadata file is included as a binary attachment to the XML version of this metadata document and also as a file named Orig_USGS_metadata.txt. The attribute definitions in the original metadata did not match the fields actually present in the data, but the mapping from metadata field name to actual field name was more or less obvious.</gco:CharacterString>
        </gmd:abstract>
        <gmd:purpose>
          <gco:CharacterString xmlns:gco="http://www.isotc211.org/2005/gco">The Geographic Names Information System contains information about physical and cultural geographic features of all types in the United States, associated areas, and Antarctica, current and historical, but not including roads and highways. The database holds the Federally recognized name of each feature and defines the feature location by state, county, USGS topographic map, and geographic coordinates. Other attributes include names or spellings other than the official name, feature designations, feature classification, historical and descriptive information, and for some categories the geometric boundaries. The database assigns a unique, permanent feature identifier, the Feature ID, as a standard Federal key for accessing, integrating, or reconciling feature data from multiple data sets. The GNIS collects data from a broad program of partnerships with Federal, State, and local government agencies and other authorized contributors. The GNIS provides data to all levels of government and to the public, as well as to numerous applications through a web query site, web map and feature services, file download services, and customized files upon request.</gco:CharacterString>
        </gmd:purpose>
        <gmd:status>
          <gmd:MD_ProgressCode codeList="http://standards.iso.org/ittf/PubliclyAvailableStandards/ISO_19139_Schemas/resources/codelist/ML_gmxCodelists.xml#MD_ProgressCode" codeListValue="underDevelopment" codeSpace="ISOTC211/19115"/>
        </gmd:status>
        <gmd:pointOfContact>
          <gmd:CI_ResponsibleParty>
            <gmd:contactInfo>
              <gmd:CI_Contact>
                <gmd:contactInstructions>
                  <gco:CharacterString xmlns:gco="http://www.isotc211.org/2005/gco">Please refer to the Distribution Information section.</gco:CharacterString>
                </gmd:contactInstructions>
              </gmd:CI_Contact>
            </gmd:contactInfo>
            <gmd:role>
              <gmd:CI_RoleCode codeList="http://standards.iso.org/ittf/PubliclyAvailableStandards/ISO_19139_Schemas/resources/codelist/ML_gmxCodelists.xml#CI_RoleCode" codeListValue="pointOfContact" codeSpace="ISOTC211/19115"/>
            </gmd:role>
          </gmd:CI_ResponsibleParty>
        </gmd:pointOfContact>
        <gmd:resourceMaintenance>
          <gmd:MD_MaintenanceInformation>
            <gmd:maintenanceAndUpdateFrequency>
              <gmd:MD_MaintenanceFrequencyCode codeList="http://standards.iso.org/ittf/PubliclyAvailableStandards/ISO_19139_Schemas/resources/codelist/ML_gmxCodelists.xml#MD_MaintenanceFrequencyCode" codeListValue="irregular" codeSpace="ISOTC211/19115"/>
            </gmd:maintenanceAndUpdateFrequency>
          </gmd:MD_MaintenanceInformation>
        </gmd:resourceMaintenance>
        <gmd:resourceConstraints>
          <gmd:MD_Constraints>
            <gmd:useLimitation>
              <gco:CharacterString xmlns:gco="http://www.isotc211.org/2005/gco">None. Acknowledgement of the U.S. Geological Survey would be appreciated in products derived from these data.</gco:CharacterString>
            </gmd:useLimitation>
          </gmd:MD_Constraints>
        </gmd:resourceConstraints>
        <gmd:resourceConstraints>
          <gmd:MD_LegalConstraints>
            <gmd:useLimitation>
              <gco:CharacterString xmlns:gco="http://www.isotc211.org/2005/gco">Refer to the Legal Notices of Terms and Conditions of the University of Illinois Web Privacy Policy (there is a link in the Cross References section) for policy statements regarding the following: Disclaimer of Liability Disclaimer of Warranties and Accuracy of Data Disclaimer of Endorsement Disclaimer for External Links Disclaimer of Duty to Continue Provision of Data Security Choice of Law By obtaining these data you agree to the provisions of the University of Illinois Web Privacy Policy, regardless of the manner in which the information was obtained.</gco:CharacterString>
            </gmd:useLimitation>
          </gmd:MD_LegalConstraints>
        </gmd:resourceConstraints>
        <gmd:aggregationInfo>
          <gmd:MD_AggregateInformation>
            <gmd:aggregateDataSetName>
              <gmd:CI_Citation>
                <gmd:title>
                  <gco:CharacterString xmlns:gco="http://www.isotc211.org/2005/gco">GEOnet Names Server</gco:CharacterString>
                </gmd:title>
                <gmd:citedResponsibleParty>
                  <gmd:CI_ResponsibleParty>
                    <gmd:organisationName>
                      <gco:CharacterString xmlns:gco="http://www.isotc211.org/2005/gco">National Geospatial Agency (NGA)</gco:CharacterString>
                    </gmd:organisationName>
                    <gmd:role>
                      <gmd:CI_RoleCode codeList="http://standards.iso.org/ittf/PubliclyAvailableStandards/ISO_19139_Schemas/resources/codelist/ML_gmxCodelists.xml#CI_RoleCode" codeListValue="originator" codeSpace="ISOTC211/19115"/>
                    </gmd:role>
                  </gmd:CI_ResponsibleParty>
                </gmd:citedResponsibleParty>
                <gmd:otherCitationDetails>
                  <gco:CharacterString xmlns:gco="http://www.isotc211.org/2005/gco">The GEOnet Names Server (GNS) provides access to the National Geospatial Agency (NGA) database of foreign geographic feature names. The database is the official repository of foreign place-name decisions approved by the U.S. Board on Geographic Names (US BGN). Approximately 20,000 of the database's features are updated monthly.</gco:CharacterString>
                </gmd:otherCitationDetails>
              </gmd:CI_Citation>
            </gmd:aggregateDataSetName>
            <gmd:associationType>
              <gmd:DS_AssociationTypeCode codeList="http://standards.iso.org/ittf/PubliclyAvailableStandards/ISO_19139_Schemas/resources/codelist/ML_gmxCodelists.xml#DS_AssociationTypeCode" codeListValue="crossReference" codeSpace="ISOTC211/19115"/>
            </gmd:associationType>
          </gmd:MD_AggregateInformation>
        </gmd:aggregationInfo>
        <gmd:aggregationInfo>
          <gmd:MD_AggregateInformation>
            <gmd:aggregateDataSetName>
              <gmd:CI_Citation>
                <gmd:title>
                  <gco:CharacterString xmlns:gco="http://www.isotc211.org/2005/gco">University of Illinois Web Privacy Notice</gco:CharacterString>
                </gmd:title>
              </gmd:CI_Citation>
            </gmd:aggregateDataSetName>
            <gmd:associationType>
              <gmd:DS_AssociationTypeCode codeList="http://standards.iso.org/ittf/PubliclyAvailableStandards/ISO_19139_Schemas/resources/codelist/ML_gmxCodelists.xml#DS_AssociationTypeCode" codeListValue="crossReference" codeSpace="ISOTC211/19115"/>
            </gmd:associationType>
          </gmd:MD_AggregateInformation>
        </gmd:aggregationInfo>
        <gmd:aggregationInfo>
          <gmd:MD_AggregateInformation>
            <gmd:aggregateDataSetName>
              <gmd:CI_Citation>
                <gmd:title>
                  <gco:CharacterString xmlns:gco="http://www.isotc211.org/2005/gco">The National Hydrography Dataset</gco:CharacterString>
                </gmd:title>
                <gmd:citedResponsibleParty>
                  <gmd:CI_ResponsibleParty>
                    <gmd:organisationName>
                      <gco:CharacterString xmlns:gco="http://www.isotc211.org/2005/gco">U.S. Geological Survey</gco:CharacterString>
                    </gmd:organisationName>
                    <gmd:role>
                      <gmd:CI_RoleCode codeList="http://standards.iso.org/ittf/PubliclyAvailableStandards/ISO_19139_Schemas/resources/codelist/ML_gmxCodelists.xml#CI_RoleCode" codeListValue="originator" codeSpace="ISOTC211/19115"/>
                    </gmd:role>
                  </gmd:CI_ResponsibleParty>
                </gmd:citedResponsibleParty>
                <gmd:otherCitationDetails>
                  <gco:CharacterString xmlns:gco="http://www.isotc211.org/2005/gco">The National Hydrography Dataset (NHD) is a comprehensive set of digital spatial data that contains information about surface water features such as lakes, ponds, streams, rivers, springs and wells. Within the NHD, surface water features are combined to form "reaches," which provide the framework for linking water-related data to the NHD surface water drainage network. These linkages enable the analysis and display of these water-related data in upstream and downstream order. The GNIS provides geographic feature name data to the National Hydrography Dataset.</gco:CharacterString>
                </gmd:otherCitationDetails>
              </gmd:CI_Citation>
            </gmd:aggregateDataSetName>
            <gmd:associationType>
              <gmd:DS_AssociationTypeCode codeList="http://standards.iso.org/ittf/PubliclyAvailableStandards/ISO_19139_Schemas/resources/codelist/ML_gmxCodelists.xml#DS_AssociationTypeCode" codeListValue="crossReference" codeSpace="ISOTC211/19115"/>
            </gmd:associationType>
          </gmd:MD_AggregateInformation>
        </gmd:aggregationInfo>
        <gmd:aggregationInfo>
          <gmd:MD_AggregateInformation>
            <gmd:aggregateDataSetName>
              <gmd:CI_Citation>
                <gmd:title>
                  <gco:CharacterString xmlns:gco="http://www.isotc211.org/2005/gco">LandView</gco:CharacterString>
                </gmd:title>
                <gmd:citedResponsibleParty>
                  <gmd:CI_ResponsibleParty>
                    <gmd:organisationName>
                      <gco:CharacterString xmlns:gco="http://www.isotc211.org/2005/gco">U.S. Census Bureau</gco:CharacterString>
                    </gmd:organisationName>
                    <gmd:role>
                      <gmd:CI_RoleCode codeList="http://standards.iso.org/ittf/PubliclyAvailableStandards/ISO_19139_Schemas/resources/codelist/ML_gmxCodelists.xml#CI_RoleCode" codeListValue="originator" codeSpace="ISOTC211/19115"/>
                    </gmd:role>
                  </gmd:CI_ResponsibleParty>
                </gmd:citedResponsibleParty>
                <gmd:otherCitationDetails>
                  <gco:CharacterString xmlns:gco="http://www.isotc211.org/2005/gco">LandView is a desktop mapping system that searches and maps selected information from the Environmental Protection Agency, the Census Bureau, and the U.S. Geological Survey. LandView contains a large subset of GNIS feature, location, and attribute data for the United States. It is available on DVD. See the LandView web site for information concerning the latest edition and ordering.</gco:CharacterString>
                </gmd:otherCitationDetails>
              </gmd:CI_Citation>
            </gmd:aggregateDataSetName>
            <gmd:associationType>
              <gmd:DS_AssociationTypeCode codeList="http://standards.iso.org/ittf/PubliclyAvailableStandards/ISO_19139_Schemas/resources/codelist/ML_gmxCodelists.xml#DS_AssociationTypeCode" codeListValue="crossReference" codeSpace="ISOTC211/19115"/>
            </gmd:associationType>
          </gmd:MD_AggregateInformation>
        </gmd:aggregationInfo>
        <gmd:aggregationInfo>
          <gmd:MD_AggregateInformation>
            <gmd:aggregateDataSetName>
              <gmd:CI_Citation>
                <gmd:title>
                  <gco:CharacterString xmlns:gco="http://www.isotc211.org/2005/gco">Geodata.gov, Geospatial One-Stop</gco:CharacterString>
                </gmd:title>
                <gmd:citedResponsibleParty>
                  <gmd:CI_ResponsibleParty>
                    <gmd:organisationName>
                      <gco:CharacterString xmlns:gco="http://www.isotc211.org/2005/gco">U.S. Geological Survey</gco:CharacterString>
                    </gmd:organisationName>
                    <gmd:role>
                      <gmd:CI_RoleCode codeList="http://standards.iso.org/ittf/PubliclyAvailableStandards/ISO_19139_Schemas/resources/codelist/ML_gmxCodelists.xml#CI_RoleCode" codeListValue="originator" codeSpace="ISOTC211/19115"/>
                    </gmd:role>
                  </gmd:CI_ResponsibleParty>
                </gmd:citedResponsibleParty>
                <gmd:otherCitationDetails>
                  <gco:CharacterString xmlns:gco="http://www.isotc211.org/2005/gco">Geodata.gov is a geographic information system (GIS) portal, also known as the Geospatial One-Stop (GOS) that serves as a public gateway for improving access to geospatial information and data under the Geospatial One-Stop E-Government initiative. Geospatial One-Stop is one of 24 E-Government initiatives sponsored by the Federal Office of Management and Budget (OMB) to enhance government efficiency and to improve citizen services. See the Geographic Names community in geodata.gov.</gco:CharacterString>
                </gmd:otherCitationDetails>
              </gmd:CI_Citation>
            </gmd:aggregateDataSetName>
            <gmd:associationType>
              <gmd:DS_AssociationTypeCode codeList="http://standards.iso.org/ittf/PubliclyAvailableStandards/ISO_19139_Schemas/resources/codelist/ML_gmxCodelists.xml#DS_AssociationTypeCode" codeListValue="crossReference" codeSpace="ISOTC211/19115"/>
            </gmd:associationType>
          </gmd:MD_AggregateInformation>
        </gmd:aggregationInfo>
        <gmd:aggregationInfo>
          <gmd:MD_AggregateInformation>
            <gmd:aggregateDataSetName>
              <gmd:CI_Citation>
                <gmd:title>
                  <gco:CharacterString xmlns:gco="http://www.isotc211.org/2005/gco">The National Atlas</gco:CharacterString>
                </gmd:title>
                <gmd:citedResponsibleParty>
                  <gmd:CI_ResponsibleParty>
                    <gmd:organisationName>
                      <gco:CharacterString xmlns:gco="http://www.isotc211.org/2005/gco">U.S. Geological Survey</gco:CharacterString>
                    </gmd:organisationName>
                    <gmd:role>
                      <gmd:CI_RoleCode codeList="http://standards.iso.org/ittf/PubliclyAvailableStandards/ISO_19139_Schemas/resources/codelist/ML_gmxCodelists.xml#CI_RoleCode" codeListValue="originator" codeSpace="ISOTC211/19115"/>
                    </gmd:role>
                  </gmd:CI_ResponsibleParty>
                </gmd:citedResponsibleParty>
                <gmd:otherCitationDetails>
                  <gco:CharacterString xmlns:gco="http://www.isotc211.org/2005/gco">The National Atlas summarizes national-scale geographical information and delivers easy to use, map-like views of America's natural and sociocultural landscapes. This digital version revises a large bound collection of paper maps that was published in 1970. The Atlas serves a diverse populace as an essential reference, a framework for information discovery, an instrument of education, an aid in research, and a reliable source of government information. It includes stimulating products and services for children and adults to understand complex relationships among environments, places, and people. It contributes to our knowledge of the environmental, resource, demographic, economic, social, political, and historical dimensions of American life. Though it cannot display detailed map information, the Atlas directs users to other sources for this information. The GNIS provides geographic feature, location, and attribute data to the National Atlas.</gco:CharacterString>
                </gmd:otherCitationDetails>
              </gmd:CI_Citation>
            </gmd:aggregateDataSetName>
            <gmd:associationType>
              <gmd:DS_AssociationTypeCode codeList="http://standards.iso.org/ittf/PubliclyAvailableStandards/ISO_19139_Schemas/resources/codelist/ML_gmxCodelists.xml#DS_AssociationTypeCode" codeListValue="crossReference" codeSpace="ISOTC211/19115"/>
            </gmd:associationType>
          </gmd:MD_AggregateInformation>
        </gmd:aggregationInfo>
        <gmd:aggregationInfo>
          <gmd:MD_AggregateInformation>
            <gmd:aggregateDataSetName>
              <gmd:CI_Citation>
                <gmd:title>
                  <gco:CharacterString xmlns:gco="http://www.isotc211.org/2005/gco">The National Map</gco:CharacterString>
                </gmd:title>
                <gmd:citedResponsibleParty>
                  <gmd:CI_ResponsibleParty>
                    <gmd:organisationName>
                      <gco:CharacterString xmlns:gco="http://www.isotc211.org/2005/gco">U.S. Geological Survey</gco:CharacterString>
                    </gmd:organisationName>
                    <gmd:role>
                      <gmd:CI_RoleCode codeList="http://standards.iso.org/ittf/PubliclyAvailableStandards/ISO_19139_Schemas/resources/codelist/ML_gmxCodelists.xml#CI_RoleCode" codeListValue="originator" codeSpace="ISOTC211/19115"/>
                    </gmd:role>
                  </gmd:CI_ResponsibleParty>
                </gmd:citedResponsibleParty>
                <gmd:otherCitationDetails>
                  <gco:CharacterString xmlns:gco="http://www.isotc211.org/2005/gco">The National Map, is a seamless, continuously maintained set of public domain geographic base information that serves as a foundation for integrating, sharing, and using other data easily and consistently. The National Map viewer is a Web-enabled portal to all of the geospatial information contained in The National Map. This portal not only supports on-line access to the geospatial information, but also allows the download of digital data and creation of cartographic products. The GNIS supports The National Map as the source for the gazetteer search in Find Place function of The National Map viewer and as active names layers.</gco:CharacterString>
                </gmd:otherCitationDetails>
              </gmd:CI_Citation>
            </gmd:aggregateDataSetName>
            <gmd:associationType>
              <gmd:DS_AssociationTypeCode codeList="http://standards.iso.org/ittf/PubliclyAvailableStandards/ISO_19139_Schemas/resources/codelist/ML_gmxCodelists.xml#DS_AssociationTypeCode" codeListValue="crossReference" codeSpace="ISOTC211/19115"/>
            </gmd:associationType>
          </gmd:MD_AggregateInformation>
        </gmd:aggregationInfo>
        <gmd:spatialRepresentationType>
          <gmd:MD_SpatialRepresentationTypeCode codeList="http://standards.iso.org/ittf/PubliclyAvailableStandards/ISO_19139_Schemas/resources/codelist/ML_gmxCodelists.xml#MD_SpatialRepresentationTypeCode" codeListValue="vector" codeSpace="ISOTC211/19115"/>
        </gmd:spatialRepresentationType>
        <gmd:language>
          <gmd:LanguageCode codeList="http://www.loc.gov/standards/iso639-2/" codeListValue="eng" codeSpace="ISO639-2"/>
        </gmd:language>
        <gmd:characterSet>
          <gmd:MD_CharacterSetCode codeList="http://standards.iso.org/ittf/PubliclyAvailableStandards/ISO_19139_Schemas/resources/codelist/ML_gmxCodelists.xml#MD_CharacterSetCode" codeListValue="utf8" codeSpace="ISOTC211/19115"/>
        </gmd:characterSet>
        <gmd:topicCategory>
          <gmd:MD_TopicCategoryCode>location</gmd:MD_TopicCategoryCode>
        </gmd:topicCategory>
        <gmd:environmentDescription>
          <gco:CharacterString xmlns:gco="http://www.isotc211.org/2005/gco">ArcSDE 9.1 on Oracle 10g</gco:CharacterString>
        </gmd:environmentDescription>
        <gmd:extent>
          <gmd:EX_Extent>
            <gmd:geographicElement>
              <gmd:EX_GeographicBoundingBox>
                <gmd:westBoundLongitude>
                  <gco:Decimal xmlns:gco="http://www.isotc211.org/2005/gco">-91.512655</gco:Decimal>
                </gmd:westBoundLongitude>
                <gmd:eastBoundLongitude>
                  <gco:Decimal xmlns:gco="http://www.isotc211.org/2005/gco">-87.375015</gco:Decimal>
                </gmd:eastBoundLongitude>
                <gmd:southBoundLatitude>
                  <gco:Decimal xmlns:gco="http://www.isotc211.org/2005/gco">36.979496</gco:Decimal>
                </gmd:southBoundLatitude>
                <gmd:northBoundLatitude>
                  <gco:Decimal xmlns:gco="http://www.isotc211.org/2005/gco">42.574729</gco:Decimal>
                </gmd:northBoundLatitude>
              </gmd:EX_GeographicBoundingBox>
            </gmd:geographicElement>
          </gmd:EX_Extent>
        </gmd:extent>
        <gmd:extent>
          <gmd:EX_Extent>
            <gmd:description>
              <gco:CharacterString xmlns:gco="http://www.isotc211.org/2005/gco">ground condition</gco:CharacterString>
            </gmd:description>
            <gmd:temporalElement>
              <gmd:EX_TemporalExtent>
                <gmd:extent>
                  <gml:TimePeriod xmlns:gml="http://www.opengis.net/gml" gml:id="d1363648e768">
                    <gml:beginPosition>1974</gml:beginPosition>
                    <gml:endPosition>2006</gml:endPosition>
                  </gml:TimePeriod>
                </gmd:extent>
              </gmd:EX_TemporalExtent>
            </gmd:temporalElement>
          </gmd:EX_Extent>
        </gmd:extent>
        <gmd:supplementalInformation>
          <gco:CharacterString xmlns:gco="http://www.isotc211.org/2005/gco">The U.S. Board on Geographic Names was created in 1890 and established in its present form by Public Law in 1947 to establish and maintain uniform geographic name usage throughout the Federal Government. The Board serves all government agencies and the public as the central authority to which name inquiries, name issues, and new name proposals can be directed. It is comprised of representatives of Federal agencies associated with land management and cartography. Sharing its responsibilities with the Secretary of the Interior, the Board develops principles, policies, and procedures governing the use of both domestic and foreign geographic names as well as undersea and Antarctic feature names.</gco:CharacterString>
        </gmd:supplementalInformation>
        <gmd:credit>
          <gco:CharacterString xmlns:gco="http://www.isotc211.org/2005/gco">Illinois</gco:CharacterString>
        </gmd:credit>
        <gmd:descriptiveKeywords>
          <gmd:MD_Keywords>
            <gmd:type>
              <gmd:MD_KeywordTypeCode codeList="http://www.isotc211.org/2005/resources/codeList.xml#MD_KeywordTypeCode" codeListValue="place"/>
            </gmd:type>
            <gmd:thesaurusName>
              <gmd:CI_Citation>
                <gmd:title>
                  <gco:CharacterString xmlns:gco="http://www.isotc211.org/2005/gco">Geonames</gco:CharacterString>
                </gmd:title>
                <gmd:date>
                  <gmd:CI_Date>
                    <gmd:date>
                      <gco:Date xmlns:gco="http://www.isotc211.org/2005/gco">2017</gco:Date>
                    </gmd:date>
                    <gmd:dateType>
                      <gmd:CI_DateTypeCode codeListValue="revision"/>
                    </gmd:dateType>
                  </gmd:CI_Date>
                </gmd:date>
                <gmd:identifier>
                  <gmd:MD_Identifier>
                    <gmd:code>
                      <gco:CharacterString xmlns:gco="http://www.isotc211.org/2005/gco">http://www.geonames.org/ontology#</gco:CharacterString>
                    </gmd:code>
                  </gmd:MD_Identifier>
                </gmd:identifier>
              </gmd:CI_Citation>
            </gmd:thesaurusName>
            <gmd:keyword>
              <gco:CharacterString xmlns:gco="http://www.isotc211.org/2005/gco">Illinois, United States</gco:CharacterString>
            </gmd:keyword>
          </gmd:MD_Keywords>
        </gmd:descriptiveKeywords>
      </gmd:MD_DataIdentification>
    </gmd:identificationInfo>
    <gmd:distributionInfo>
      <gmd:MD_Distribution>
        <gmd:distributor>
          <gmd:MD_Distributor>
            <gmd:distributorContact>
              <gmd:CI_ResponsibleParty>
                <gmd:organisationName>
                  <gco:CharacterString xmlns:gco="http://www.isotc211.org/2005/gco">Information Office, Illinois State Geological Survey (ISGS), a division of the Institute of Natural Resource Sustainability (INRS) of the University of Illinois</gco:CharacterString>
                </gmd:organisationName>
                <gmd:contactInfo>
                  <gmd:CI_Contact>
                    <gmd:phone>
                      <gmd:CI_Telephone>
                        <gmd:voice>
                          <gco:CharacterString xmlns:gco="http://www.isotc211.org/2005/gco">217-333-4747</gco:CharacterString>
                        </gmd:voice>
                        <gmd:voice>
                          <gco:CharacterString xmlns:gco="http://www.isotc211.org/2005/gco">217-785-0211</gco:CharacterString>
                        </gmd:voice>
                      </gmd:CI_Telephone>
                    </gmd:phone>
                    <gmd:address>
                      <gmd:CI_Address>
                        <gmd:deliveryPoint>
                          <gco:CharacterString xmlns:gco="http://www.isotc211.org/2005/gco">615 East Peabody Drive</gco:CharacterString>
                        </gmd:deliveryPoint>
                        <gmd:city>
                          <gco:CharacterString xmlns:gco="http://www.isotc211.org/2005/gco">Champaign</gco:CharacterString>
                        </gmd:city>
                        <gmd:administrativeArea>
                          <gco:CharacterString xmlns:gco="http://www.isotc211.org/2005/gco">Illinois</gco:CharacterString>
                        </gmd:administrativeArea>
                        <gmd:postalCode>
                          <gco:CharacterString xmlns:gco="http://www.isotc211.org/2005/gco">61820</gco:CharacterString>
                        </gmd:postalCode>
                        <gmd:country>
                          <gco:CharacterString xmlns:gco="http://www.isotc211.org/2005/gco">US</gco:CharacterString>
                        </gmd:country>
                        <gmd:electronicMailAddress>
                          <gco:CharacterString xmlns:gco="http://www.isotc211.org/2005/gco">isgs@isgs.illinois.edu</gco:CharacterString>
                        </gmd:electronicMailAddress>
                      </gmd:CI_Address>
                    </gmd:address>
                    <gmd:hoursOfService>
                      <gco:CharacterString xmlns:gco="http://www.isotc211.org/2005/gco">8:00 a.m. - 4:30 p.m., Monday-Friday, U.S. Central Time</gco:CharacterString>
                    </gmd:hoursOfService>
                  </gmd:CI_Contact>
                </gmd:contactInfo>
                <gmd:role>
                  <gmd:CI_RoleCode codeList="http://standards.iso.org/ittf/PubliclyAvailableStandards/ISO_19139_Schemas/resources/codelist/ML_gmxCodelists.xml#CI_RoleCode" codeListValue="distributor" codeSpace="ISOTC211/19115"/>
                </gmd:role>
              </gmd:CI_ResponsibleParty>
            </gmd:distributorContact>
          </gmd:MD_Distributor>
        </gmd:distributor>
        <gmd:transferOptions>
          <gmd:MD_DigitalTransferOptions>
            <gmd:onLine>
              <gmd:CI_OnlineResource>
                <gmd:linkage>
                  <gmd:URL>https://clearinghouse.isgs.illinois.edu/data/infrastructure/us-geographic-names-information-system-gnis-illinois</gmd:URL>
                </gmd:linkage>
                <gmd:protocol>
                  <gco:CharacterString xmlns:gco="http://www.isotc211.org/2005/gco">WWW:LINK</gco:CharacterString>
                </gmd:protocol>
              </gmd:CI_OnlineResource>
            </gmd:onLine>
            <gmd:onLine>
              <gmd:CI_OnlineResource>
                <gmd:linkage>
                  <gmd:URL>https://clearinghouse.isgs.illinois.edu/sites/clearinghouse.isgs/files/Clearinghouse/data/ISGS/Infrastructure/zips/IL_GNIS_2006_Pt.zip</gmd:URL>
                </gmd:linkage>
                <gmd:protocol>
                  <gco:CharacterString xmlns:gco="http://www.isotc211.org/2005/gco">WWW:DOWNLOAD-1.0-ftp--download</gco:CharacterString>
                </gmd:protocol>
              </gmd:CI_OnlineResource>
            </gmd:onLine>
          </gmd:MD_DigitalTransferOptions>
        </gmd:transferOptions>
        <gmd:distributionFormat>
          <gmd:MD_Format>
            <gmd:name>
              <gco:CharacterString xmlns:gco="http://www.isotc211.org/2005/gco">Shapefile</gco:CharacterString>
            </gmd:name>
          </gmd:MD_Format>
        </gmd:distributionFormat>
      </gmd:MD_Distribution>
    </gmd:distributionInfo>
    <gmd:dataQualityInfo>
      <gmd:DQ_DataQuality>
        <gmd:scope>
          <gmd:DQ_Scope>
            <gmd:level>
              <gmd:MD_ScopeCode codeList="http://standards.iso.org/ittf/PubliclyAvailableStandards/ISO_19139_Schemas/resources/codelist/ML_gmxCodelists.xml#MD_ScopeCode" codeListValue="dataset" codeSpace="ISOTC211/19115"/>
            </gmd:level>
          </gmd:DQ_Scope>
        </gmd:scope>
        <gmd:report>
          <gmd:DQ_TopologicalConsistency>
            <gmd:evaluationMethodDescription>
              <gco:CharacterString xmlns:gco="http://www.isotc211.org/2005/gco">During Phase I data compilation, a random sample of 10% of the entries in the system were visually verified against the compilation source data (large-scale USGS topographic maps) to ensure logical consistency of locative references (geographic coordinates, topographic map, and county. Subsequent data compilation and input processes include programmed validation checks for logical consistency, visual examination, and spot checks of data.</gco:CharacterString>
            </gmd:evaluationMethodDescription>
          </gmd:DQ_TopologicalConsistency>
        </gmd:report>
        <gmd:report>
          <gmd:DQ_ConceptualConsistency>
            <gmd:measureDescription>
              <gco:CharacterString xmlns:gco="http://www.isotc211.org/2005/gco">During Phase I data compilation, a random sample of 10% of the entries in the system were visually verified against the compilation source data (large-scale USGS topographic maps) to ensure logical consistency of locative references (geographic coordinates, topographic map, and county. Subsequent data compilation and input processes include programmed validation checks for logical consistency, visual examination, and spot checks of data.</gco:CharacterString>
            </gmd:measureDescription>
          </gmd:DQ_ConceptualConsistency>
        </gmd:report>
        <gmd:report>
          <gmd:DQ_CompletenessOmission>
            <gmd:measureDescription>
              <gco:CharacterString xmlns:gco="http://www.isotc211.org/2005/gco">The data points are limited to Illinois. Here is the statement that was included with the GNIS metadata. This dataset contains information about United States physical and cultural geographic features of all types and classes, with the exception of most roads and highways. Subsequent to the original data compilation process, which was taken primarily from Federal maps, the GNIS has become dependent on input from Federal, State, county, and local government agencies and other approved sources. The completeness, currency, and accuracy of the data varies by area depending on the quality and timeliness of that input. Accordingly, the Geographic Names Project actively seeks to expand partnerships with Government agencies at all levels and other interested organizations. The latest tools and methodologies are being applied, including web map and feature services, and joint or linked web applications, to ensure that local data are properly represented in the GNIS and through the GNIS to all Federal agencies and to the public. Feature additions or corrections are accepted for consideration from any source, and when validated by appropriate agencies, will be entered into the database. Local and State agencies are encouraged to submit data and to participate in the GNIS partnership program. Non-government organizations with valuable data are considered on a case basis. Authorized partners have access to web based transaction entry and edit forms, which submit data directly to the GNIS for review and inclusion in the database. Partners also submit batch files in most standard formats, and coordinate with the Geographic Names Project to develop joint services, processes, and applications for greatest efficiency. Data entered into the GNIS immediately is available to all web services and applications dependent on it. For additional information or to request user accounts for entry and edit of production data and web seminar training, contact gnis_manager@usgs.gov.</gco:CharacterString>
            </gmd:measureDescription>
          </gmd:DQ_CompletenessOmission>
        </gmd:report>
        <gmd:report>
          <gmd:DQ_QuantitativeAttributeAccuracy>
            <gmd:measureDescription>
              <gco:CharacterString xmlns:gco="http://www.isotc211.org/2005/gco">During Phase I data compilation, a random sample of 10% of the entries in the system were visually verified against the compilation source data (large-scale USGS topographic maps) to ensure an accuracy rate of at least 95%. Subsequent data compilation and input processes ensure accuracy with programmed validation checks for format and content, visual examination, and spot checks of data.</gco:CharacterString>
            </gmd:measureDescription>
          </gmd:DQ_QuantitativeAttributeAccuracy>
        </gmd:report>
        <gmd:report>
          <gmd:DQ_AbsoluteExternalPositionalAccuracy>
            <gmd:measureDescription>
              <gco:CharacterString xmlns:gco="http://www.isotc211.org/2005/gco">Accuracy of these digital data is based upon the use of printed or electronic source graphics which are compiled to meet National Map Accuracy Standards. Comparison to the graphic source is used as control to assess digital positional accuracy.</gco:CharacterString>
            </gmd:measureDescription>
          </gmd:DQ_AbsoluteExternalPositionalAccuracy>
        </gmd:report>
        <gmd:lineage>
          <gmd:LI_Lineage>
            <gmd:processStep>
              <gmd:LI_ProcessStep>
                <gmd:description>
                  <gco:CharacterString xmlns:gco="http://www.isotc211.org/2005/gco">GNIS Phase II data compilation and edit - Feature name and attribute data are collected from official state and local sources and other approved sources including historical maps and documents.</gco:CharacterString>
                </gmd:description>
                <gmd:processor>
                  <gmd:CI_ResponsibleParty>
                    <gmd:individualName>
                      <gco:CharacterString xmlns:gco="http://www.isotc211.org/2005/gco">Roger L. Payne</gco:CharacterString>
                    </gmd:individualName>
                    <gmd:organisationName>
                      <gco:CharacterString xmlns:gco="http://www.isotc211.org/2005/gco">U.S. Geological Survey</gco:CharacterString>
                    </gmd:organisationName>
                    <gmd:positionName>
                      <gco:CharacterString xmlns:gco="http://www.isotc211.org/2005/gco">Chief, Geographic Names Project</gco:CharacterString>
                    </gmd:positionName>
                    <gmd:contactInfo>
                      <gmd:CI_Contact>
                        <gmd:phone>
                          <gmd:CI_Telephone>
                            <gmd:voice>
                              <gco:CharacterString xmlns:gco="http://www.isotc211.org/2005/gco">703 648 4544</gco:CharacterString>
                            </gmd:voice>
                          </gmd:CI_Telephone>
                        </gmd:phone>
                        <gmd:address>
                          <gmd:CI_Address>
                            <gmd:deliveryPoint>
                              <gco:CharacterString xmlns:gco="http://www.isotc211.org/2005/gco">523 National Center</gco:CharacterString>
                            </gmd:deliveryPoint>
                            <gmd:city>
                              <gco:CharacterString xmlns:gco="http://www.isotc211.org/2005/gco">Reston</gco:CharacterString>
                            </gmd:city>
                            <gmd:administrativeArea>
                              <gco:CharacterString xmlns:gco="http://www.isotc211.org/2005/gco">Virginia</gco:CharacterString>
                            </gmd:administrativeArea>
                            <gmd:postalCode>
                              <gco:CharacterString xmlns:gco="http://www.isotc211.org/2005/gco">20192</gco:CharacterString>
                            </gmd:postalCode>
                            <gmd:electronicMailAddress>
                              <gco:CharacterString xmlns:gco="http://www.isotc211.org/2005/gco">gnis_manager@usgs.gov</gco:CharacterString>
                            </gmd:electronicMailAddress>
                          </gmd:CI_Address>
                        </gmd:address>
                        <gmd:hoursOfService>
                          <gco:CharacterString xmlns:gco="http://www.isotc211.org/2005/gco">Monday through Friday 0730-1700 Eastern Time</gco:CharacterString>
                        </gmd:hoursOfService>
                      </gmd:CI_Contact>
                    </gmd:contactInfo>
                    <gmd:role>
                      <gmd:CI_RoleCode codeList="http://standards.iso.org/ittf/PubliclyAvailableStandards/ISO_19139_Schemas/resources/codelist/ML_gmxCodelists.xml#CI_RoleCode" codeListValue="processor" codeSpace="ISOTC211/19115"/>
                    </gmd:role>
                  </gmd:CI_ResponsibleParty>
                </gmd:processor>
                <gmd:source>
                  <gmd:LI_Source>
                    <gmd:sourceCitation>
                      <gmd:CI_Citation>
                        <gmd:alternateTitle>
                          <gco:CharacterString xmlns:gco="http://www.isotc211.org/2005/gco">USGS</gco:CharacterString>
                        </gmd:alternateTitle>
                      </gmd:CI_Citation>
                    </gmd:sourceCitation>
                  </gmd:LI_Source>
                </gmd:source>
                <gmd:source>
                  <gmd:LI_Source>
                    <gmd:sourceCitation>
                      <gmd:CI_Citation>
                        <gmd:alternateTitle>
                          <gco:CharacterString xmlns:gco="http://www.isotc211.org/2005/gco">USBGN</gco:CharacterString>
                        </gmd:alternateTitle>
                      </gmd:CI_Citation>
                    </gmd:sourceCitation>
                  </gmd:LI_Source>
                </gmd:source>
              </gmd:LI_ProcessStep>
            </gmd:processStep>
            <gmd:processStep>
              <gmd:LI_ProcessStep>
                <gmd:description>
                  <gco:CharacterString xmlns:gco="http://www.isotc211.org/2005/gco">GNIS Maintenance program - Federal and state maintenance cooperators submit new and corrected data in conjunction with their mapping and geographical information system data maintenance programs. The GNIS has an active data gathering and maintenance program. A web-based data date entry and edit application allows authorized users to submit transaction data directly for validation and entry into the database, where it immediately becomes available to all web services and applications. A test and demonstration site with no connection to production data is available for review, training, and familiarization. Batch files will be accepted in most standard formats. Government agencies at all levels are encouraged to join this program. Other organizations and individuals will be considered on a case basis. For additional information or to request user accounts for entry and edit of production data and web seminar training, contact gnis_manager@usgs.gov or the individual below.</gco:CharacterString>
                </gmd:description>
                <gmd:processor>
                  <gmd:CI_ResponsibleParty>
                    <gmd:individualName>
                      <gco:CharacterString xmlns:gco="http://www.isotc211.org/2005/gco">Louis A. Yost</gco:CharacterString>
                    </gmd:individualName>
                    <gmd:organisationName>
                      <gco:CharacterString xmlns:gco="http://www.isotc211.org/2005/gco">U.S. Geological Survey</gco:CharacterString>
                    </gmd:organisationName>
                    <gmd:positionName>
                      <gco:CharacterString xmlns:gco="http://www.isotc211.org/2005/gco">Chief, Geographic Names Information Section</gco:CharacterString>
                    </gmd:positionName>
                    <gmd:contactInfo>
                      <gmd:CI_Contact>
                        <gmd:phone>
                          <gmd:CI_Telephone>
                            <gmd:voice>
                              <gco:CharacterString xmlns:gco="http://www.isotc211.org/2005/gco">703 648 4552</gco:CharacterString>
                            </gmd:voice>
                          </gmd:CI_Telephone>
                        </gmd:phone>
                        <gmd:address>
                          <gmd:CI_Address>
                            <gmd:deliveryPoint>
                              <gco:CharacterString xmlns:gco="http://www.isotc211.org/2005/gco">523 National Center</gco:CharacterString>
                            </gmd:deliveryPoint>
                            <gmd:city>
                              <gco:CharacterString xmlns:gco="http://www.isotc211.org/2005/gco">Reston</gco:CharacterString>
                            </gmd:city>
                            <gmd:administrativeArea>
                              <gco:CharacterString xmlns:gco="http://www.isotc211.org/2005/gco">Virginia</gco:CharacterString>
                            </gmd:administrativeArea>
                            <gmd:postalCode>
                              <gco:CharacterString xmlns:gco="http://www.isotc211.org/2005/gco">20192</gco:CharacterString>
                            </gmd:postalCode>
                            <gmd:electronicMailAddress>
                              <gco:CharacterString xmlns:gco="http://www.isotc211.org/2005/gco">lyost@usgs.gov</gco:CharacterString>
                            </gmd:electronicMailAddress>
                          </gmd:CI_Address>
                        </gmd:address>
                        <gmd:hoursOfService>
                          <gco:CharacterString xmlns:gco="http://www.isotc211.org/2005/gco">0900-1700 Eastern time</gco:CharacterString>
                        </gmd:hoursOfService>
                      </gmd:CI_Contact>
                    </gmd:contactInfo>
                    <gmd:role>
                      <gmd:CI_RoleCode codeList="http://standards.iso.org/ittf/PubliclyAvailableStandards/ISO_19139_Schemas/resources/codelist/ML_gmxCodelists.xml#CI_RoleCode" codeListValue="processor" codeSpace="ISOTC211/19115"/>
                    </gmd:role>
                  </gmd:CI_ResponsibleParty>
                </gmd:processor>
                <gmd:source>
                  <gmd:LI_Source>
                    <gmd:sourceCitation>
                      <gmd:CI_Citation>
                        <gmd:alternateTitle>
                          <gco:CharacterString xmlns:gco="http://www.isotc211.org/2005/gco">NOAA/NOS</gco:CharacterString>
                        </gmd:alternateTitle>
                      </gmd:CI_Citation>
                    </gmd:sourceCitation>
                  </gmd:LI_Source>
                </gmd:source>
                <gmd:source>
                  <gmd:LI_Source>
                    <gmd:sourceCitation>
                      <gmd:CI_Citation>
                        <gmd:alternateTitle>
                          <gco:CharacterString xmlns:gco="http://www.isotc211.org/2005/gco">Various</gco:CharacterString>
                        </gmd:alternateTitle>
                      </gmd:CI_Citation>
                    </gmd:sourceCitation>
                  </gmd:LI_Source>
                </gmd:source>
                <gmd:source>
                  <gmd:LI_Source>
                    <gmd:sourceCitation>
                      <gmd:CI_Citation>
                        <gmd:alternateTitle>
                          <gco:CharacterString xmlns:gco="http://www.isotc211.org/2005/gco">USGS</gco:CharacterString>
                        </gmd:alternateTitle>
                      </gmd:CI_Citation>
                    </gmd:sourceCitation>
                  </gmd:LI_Source>
                </gmd:source>
                <gmd:source>
                  <gmd:LI_Source>
                    <gmd:sourceCitation>
                      <gmd:CI_Citation>
                        <gmd:alternateTitle>
                          <gco:CharacterString xmlns:gco="http://www.isotc211.org/2005/gco">USFS</gco:CharacterString>
                        </gmd:alternateTitle>
                      </gmd:CI_Citation>
                    </gmd:sourceCitation>
                  </gmd:LI_Source>
                </gmd:source>
                <gmd:source>
                  <gmd:LI_Source>
                    <gmd:sourceCitation>
                      <gmd:CI_Citation>
                        <gmd:alternateTitle>
                          <gco:CharacterString xmlns:gco="http://www.isotc211.org/2005/gco">USBGN</gco:CharacterString>
                        </gmd:alternateTitle>
                      </gmd:CI_Citation>
                    </gmd:sourceCitation>
                  </gmd:LI_Source>
                </gmd:source>
              </gmd:LI_ProcessStep>
            </gmd:processStep>
            <gmd:processStep>
              <gmd:LI_ProcessStep>
                <gmd:description>
                  <gco:CharacterString xmlns:gco="http://www.isotc211.org/2005/gco">Partnerships - the Geographic Names Project enters into partnerships with State names authorities and State and local GIS agencies to integrate name, location, and attribute data in the GNIS with State and local datasets. These partnerships utilize GIS and web technology to automate and simplify data maintenance, ensure data consistency, integrity, and accuracy, and meet the requirements of the Board on Geographic Names for national names standardization. Government agencies at all levels are encouraged to join this program. Other organizations and individuals will be considered on a case basis. For additional information contact the individual below.</gco:CharacterString>
                </gmd:description>
                <gmd:processor>
                  <gmd:CI_ResponsibleParty>
                    <gmd:individualName>
                      <gco:CharacterString xmlns:gco="http://www.isotc211.org/2005/gco">Roger L. Payne</gco:CharacterString>
                    </gmd:individualName>
                    <gmd:organisationName>
                      <gco:CharacterString xmlns:gco="http://www.isotc211.org/2005/gco">U.S. Geological Survey</gco:CharacterString>
                    </gmd:organisationName>
                    <gmd:positionName>
                      <gco:CharacterString xmlns:gco="http://www.isotc211.org/2005/gco">Chief, Geographic Names Project</gco:CharacterString>
                    </gmd:positionName>
                    <gmd:contactInfo>
                      <gmd:CI_Contact>
                        <gmd:phone>
                          <gmd:CI_Telephone>
                            <gmd:voice>
                              <gco:CharacterString xmlns:gco="http://www.isotc211.org/2005/gco">703 648 4544</gco:CharacterString>
                            </gmd:voice>
                          </gmd:CI_Telephone>
                        </gmd:phone>
                        <gmd:address>
                          <gmd:CI_Address>
                            <gmd:deliveryPoint>
                              <gco:CharacterString xmlns:gco="http://www.isotc211.org/2005/gco">523 National Center</gco:CharacterString>
                            </gmd:deliveryPoint>
                            <gmd:city>
                              <gco:CharacterString xmlns:gco="http://www.isotc211.org/2005/gco">Reston</gco:CharacterString>
                            </gmd:city>
                            <gmd:administrativeArea>
                              <gco:CharacterString xmlns:gco="http://www.isotc211.org/2005/gco">Virginia</gco:CharacterString>
                            </gmd:administrativeArea>
                            <gmd:postalCode>
                              <gco:CharacterString xmlns:gco="http://www.isotc211.org/2005/gco">20192</gco:CharacterString>
                            </gmd:postalCode>
                            <gmd:electronicMailAddress>
                              <gco:CharacterString xmlns:gco="http://www.isotc211.org/2005/gco">gnis_manager@usgs.gov</gco:CharacterString>
                            </gmd:electronicMailAddress>
                          </gmd:CI_Address>
                        </gmd:address>
                        <gmd:hoursOfService>
                          <gco:CharacterString xmlns:gco="http://www.isotc211.org/2005/gco">Monday through Friday 0730-1700 Eastern Time</gco:CharacterString>
                        </gmd:hoursOfService>
                      </gmd:CI_Contact>
                    </gmd:contactInfo>
                    <gmd:role>
                      <gmd:CI_RoleCode codeList="http://standards.iso.org/ittf/PubliclyAvailableStandards/ISO_19139_Schemas/resources/codelist/ML_gmxCodelists.xml#CI_RoleCode" codeListValue="processor" codeSpace="ISOTC211/19115"/>
                    </gmd:role>
                  </gmd:CI_ResponsibleParty>
                </gmd:processor>
              </gmd:LI_ProcessStep>
            </gmd:processStep>
            <gmd:processStep>
              <gmd:LI_ProcessStep>
                <gmd:description>
                  <gco:CharacterString xmlns:gco="http://www.isotc211.org/2005/gco">GNIS Phase I data compilation and edit - Feature name and attribute data were collected from the largest-scale USGS topographic maps available. These data are compared to the records of the U.S. Board on Geographic Names.</gco:CharacterString>
                </gmd:description>
                <gmd:dateTime>
                  <gco:DateTime xmlns:gco="http://www.isotc211.org/2005/gco">1981-05-01T00:00:00</gco:DateTime>
                </gmd:dateTime>
                <gmd:processor>
                  <gmd:CI_ResponsibleParty>
                    <gmd:individualName>
                      <gco:CharacterString xmlns:gco="http://www.isotc211.org/2005/gco">Roger L. Payne</gco:CharacterString>
                    </gmd:individualName>
                    <gmd:organisationName>
                      <gco:CharacterString xmlns:gco="http://www.isotc211.org/2005/gco">U.S. Geological Survey</gco:CharacterString>
                    </gmd:organisationName>
                    <gmd:positionName>
                      <gco:CharacterString xmlns:gco="http://www.isotc211.org/2005/gco">Chief, Geographic Names Project</gco:CharacterString>
                    </gmd:positionName>
                    <gmd:contactInfo>
                      <gmd:CI_Contact>
                        <gmd:phone>
                          <gmd:CI_Telephone>
                            <gmd:voice>
                              <gco:CharacterString xmlns:gco="http://www.isotc211.org/2005/gco">703 648 4544</gco:CharacterString>
                            </gmd:voice>
                          </gmd:CI_Telephone>
                        </gmd:phone>
                        <gmd:address>
                          <gmd:CI_Address>
                            <gmd:deliveryPoint>
                              <gco:CharacterString xmlns:gco="http://www.isotc211.org/2005/gco">523 National Center</gco:CharacterString>
                            </gmd:deliveryPoint>
                            <gmd:city>
                              <gco:CharacterString xmlns:gco="http://www.isotc211.org/2005/gco">Reston</gco:CharacterString>
                            </gmd:city>
                            <gmd:administrativeArea>
                              <gco:CharacterString xmlns:gco="http://www.isotc211.org/2005/gco">Virginia</gco:CharacterString>
                            </gmd:administrativeArea>
                            <gmd:postalCode>
                              <gco:CharacterString xmlns:gco="http://www.isotc211.org/2005/gco">20192</gco:CharacterString>
                            </gmd:postalCode>
                            <gmd:electronicMailAddress>
                              <gco:CharacterString xmlns:gco="http://www.isotc211.org/2005/gco">gnis_manager@usgs.gov</gco:CharacterString>
                            </gmd:electronicMailAddress>
                          </gmd:CI_Address>
                        </gmd:address>
                        <gmd:hoursOfService>
                          <gco:CharacterString xmlns:gco="http://www.isotc211.org/2005/gco">Monday through Friday 0730-1700 Eastern Time</gco:CharacterString>
                        </gmd:hoursOfService>
                      </gmd:CI_Contact>
                    </gmd:contactInfo>
                    <gmd:role>
                      <gmd:CI_RoleCode codeList="http://standards.iso.org/ittf/PubliclyAvailableStandards/ISO_19139_Schemas/resources/codelist/ML_gmxCodelists.xml#CI_RoleCode" codeListValue="processor" codeSpace="ISOTC211/19115"/>
                    </gmd:role>
                  </gmd:CI_ResponsibleParty>
                </gmd:processor>
                <gmd:source>
                  <gmd:LI_Source>
                    <gmd:sourceCitation>
                      <gmd:CI_Citation>
                        <gmd:alternateTitle>
                          <gco:CharacterString xmlns:gco="http://www.isotc211.org/2005/gco">USGS</gco:CharacterString>
                        </gmd:alternateTitle>
                      </gmd:CI_Citation>
                    </gmd:sourceCitation>
                  </gmd:LI_Source>
                </gmd:source>
                <gmd:source>
                  <gmd:LI_Source>
                    <gmd:sourceCitation>
                      <gmd:CI_Citation>
                        <gmd:alternateTitle>
                          <gco:CharacterString xmlns:gco="http://www.isotc211.org/2005/gco">USBGN</gco:CharacterString>
                        </gmd:alternateTitle>
                      </gmd:CI_Citation>
                    </gmd:sourceCitation>
                  </gmd:LI_Source>
                </gmd:source>
              </gmd:LI_ProcessStep>
            </gmd:processStep>
            <gmd:processStep>
              <gmd:LI_ProcessStep>
                <gmd:description>
                  <gco:CharacterString xmlns:gco="http://www.isotc211.org/2005/gco">The data in tab-delimited text format were downloaded from the GNIS website. The data were imported into an Excel spreadsheet and exported as comma-delimited. The comma-delimited text file was loaded into ArcMap and displayed as an XY Event Theme based on the fields Primary_lon_dec and Primary_lat_dec. NAD83 was assumed. The event theme was exported to a personal geodatabase feature class. Eight obviously erroneous points falling far outside Illinois were deleted. Points falling outside Illinois but relatively close to the Illinois state boundary were retained. The personal geodatabase feature class was imported into ArcSDE and analyzed. The GNIS metadata was downloaded from http://geonames.usgs.gov/docs/metadata/gnis.txt and updated with ISGS-specific information. The original metadata file is included as a binary attachment to the XML version of this metadata document. The attribute definitions in the original metadata did not match the fields actually present in the data, but the mapping from metadata field name to actual field name was more or less obvious.</gco:CharacterString>
                </gmd:description>
                <gmd:dateTime>
                  <gco:DateTime xmlns:gco="http://www.isotc211.org/2005/gco">2006-08-24T00:00:00</gco:DateTime>
                </gmd:dateTime>
                <gmd:processor>
                  <gmd:CI_ResponsibleParty>
                    <gmd:role>
                      <gmd:CI_RoleCode codeList="http://standards.iso.org/ittf/PubliclyAvailableStandards/ISO_19139_Schemas/resources/codelist/ML_gmxCodelists.xml#CI_RoleCode" codeListValue="processor" codeSpace="ISOTC211/19115"/>
                    </gmd:role>
                  </gmd:CI_ResponsibleParty>
                </gmd:processor>
              </gmd:LI_ProcessStep>
            </gmd:processStep>
            <gmd:source>
              <gmd:LI_Source>
                <gmd:description>
                  <gco:CharacterString xmlns:gco="http://www.isotc211.org/2005/gco">Feature names and attribute information</gco:CharacterString>
                </gmd:description>
                <gmd:scaleDenominator>
                  <gmd:MD_RepresentativeFraction>
                    <gmd:denominator>
                      <gco:Integer xmlns:gco="http://www.isotc211.org/2005/gco">24000</gco:Integer>
                    </gmd:denominator>
                  </gmd:MD_RepresentativeFraction>
                </gmd:scaleDenominator>
                <gmd:sourceCitation>
                  <gmd:CI_Citation>
                    <gmd:title>
                      <gco:CharacterString xmlns:gco="http://www.isotc211.org/2005/gco">U.S. Forest Service 1:24,000-scale topographic maps and visitor maps</gco:CharacterString>
                    </gmd:title>
                    <gmd:alternateTitle>
                      <gco:CharacterString xmlns:gco="http://www.isotc211.org/2005/gco">USFS</gco:CharacterString>
                    </gmd:alternateTitle>
                    <gmd:citedResponsibleParty>
                      <gmd:CI_ResponsibleParty>
                        <gmd:organisationName>
                          <gco:CharacterString xmlns:gco="http://www.isotc211.org/2005/gco">U.S. Forest Service</gco:CharacterString>
                        </gmd:organisationName>
                        <gmd:role>
                          <gmd:CI_RoleCode codeList="http://standards.iso.org/ittf/PubliclyAvailableStandards/ISO_19139_Schemas/resources/codelist/ML_gmxCodelists.xml#CI_RoleCode" codeListValue="originator" codeSpace="ISOTC211/19115"/>
                        </gmd:role>
                      </gmd:CI_ResponsibleParty>
                    </gmd:citedResponsibleParty>
                  </gmd:CI_Citation>
                </gmd:sourceCitation>
                <gmd:sourceExtent>
                  <gmd:EX_Extent>
                    <gmd:description>
                      <gco:CharacterString xmlns:gco="http://www.isotc211.org/2005/gco">Publication date</gco:CharacterString>
                    </gmd:description>
                    <gmd:temporalElement>
                      <gmd:EX_TemporalExtent>
                        <gmd:extent>
                          <gml:TimePeriod xmlns:gml="http://www.opengis.net/gml" gml:id="d1363648e1278">
                            <gml:beginPosition indeterminatePosition="unknown"/>
                            <gml:endPosition indeterminatePosition="now"/>
                          </gml:TimePeriod>
                        </gmd:extent>
                      </gmd:EX_TemporalExtent>
                    </gmd:temporalElement>
                  </gmd:EX_Extent>
                </gmd:sourceExtent>
              </gmd:LI_Source>
            </gmd:source>
            <gmd:source>
              <gmd:LI_Source>
                <gmd:description>
                  <gco:CharacterString xmlns:gco="http://www.isotc211.org/2005/gco">Feature names and attribute information</gco:CharacterString>
                </gmd:description>
                <gmd:sourceCitation>
                  <gmd:CI_Citation>
                    <gmd:title>
                      <gco:CharacterString xmlns:gco="http://www.isotc211.org/2005/gco">Unknown</gco:CharacterString>
                    </gmd:title>
                    <gmd:alternateTitle>
                      <gco:CharacterString xmlns:gco="http://www.isotc211.org/2005/gco">Various</gco:CharacterString>
                    </gmd:alternateTitle>
                    <gmd:citedResponsibleParty>
                      <gmd:CI_ResponsibleParty>
                        <gmd:organisationName>
                          <gco:CharacterString xmlns:gco="http://www.isotc211.org/2005/gco">Council of Geographic Names Authorities (COGNA)</gco:CharacterString>
                        </gmd:organisationName>
                        <gmd:role>
                          <gmd:CI_RoleCode codeList="http://standards.iso.org/ittf/PubliclyAvailableStandards/ISO_19139_Schemas/resources/codelist/ML_gmxCodelists.xml#CI_RoleCode" codeListValue="originator" codeSpace="ISOTC211/19115"/>
                        </gmd:role>
                      </gmd:CI_ResponsibleParty>
                    </gmd:citedResponsibleParty>
                    <gmd:citedResponsibleParty>
                      <gmd:CI_ResponsibleParty>
                        <gmd:organisationName>
                          <gco:CharacterString xmlns:gco="http://www.isotc211.org/2005/gco">National Park Service (NPS)</gco:CharacterString>
                        </gmd:organisationName>
                        <gmd:role>
                          <gmd:CI_RoleCode codeList="http://standards.iso.org/ittf/PubliclyAvailableStandards/ISO_19139_Schemas/resources/codelist/ML_gmxCodelists.xml#CI_RoleCode" codeListValue="originator" codeSpace="ISOTC211/19115"/>
                        </gmd:role>
                      </gmd:CI_ResponsibleParty>
                    </gmd:citedResponsibleParty>
                    <gmd:citedResponsibleParty>
                      <gmd:CI_ResponsibleParty>
                        <gmd:organisationName>
                          <gco:CharacterString xmlns:gco="http://www.isotc211.org/2005/gco">Public</gco:CharacterString>
                        </gmd:organisationName>
                        <gmd:role>
                          <gmd:CI_RoleCode codeList="http://standards.iso.org/ittf/PubliclyAvailableStandards/ISO_19139_Schemas/resources/codelist/ML_gmxCodelists.xml#CI_RoleCode" codeListValue="originator" codeSpace="ISOTC211/19115"/>
                        </gmd:role>
                      </gmd:CI_ResponsibleParty>
                    </gmd:citedResponsibleParty>
                    <gmd:citedResponsibleParty>
                      <gmd:CI_ResponsibleParty>
                        <gmd:organisationName>
                          <gco:CharacterString xmlns:gco="http://www.isotc211.org/2005/gco">Other Federal, state and local agencies</gco:CharacterString>
                        </gmd:organisationName>
                        <gmd:role>
                          <gmd:CI_RoleCode codeList="http://standards.iso.org/ittf/PubliclyAvailableStandards/ISO_19139_Schemas/resources/codelist/ML_gmxCodelists.xml#CI_RoleCode" codeListValue="originator" codeSpace="ISOTC211/19115"/>
                        </gmd:role>
                      </gmd:CI_ResponsibleParty>
                    </gmd:citedResponsibleParty>
                    <gmd:citedResponsibleParty>
                      <gmd:CI_ResponsibleParty>
                        <gmd:organisationName>
                          <gco:CharacterString xmlns:gco="http://www.isotc211.org/2005/gco">U.S. Forest Service</gco:CharacterString>
                        </gmd:organisationName>
                        <gmd:role>
                          <gmd:CI_RoleCode codeList="http://standards.iso.org/ittf/PubliclyAvailableStandards/ISO_19139_Schemas/resources/codelist/ML_gmxCodelists.xml#CI_RoleCode" codeListValue="originator" codeSpace="ISOTC211/19115"/>
                        </gmd:role>
                      </gmd:CI_ResponsibleParty>
                    </gmd:citedResponsibleParty>
                    <gmd:citedResponsibleParty>
                      <gmd:CI_ResponsibleParty>
                        <gmd:organisationName>
                          <gco:CharacterString xmlns:gco="http://www.isotc211.org/2005/gco">The State Names Authorities</gco:CharacterString>
                        </gmd:organisationName>
                        <gmd:role>
                          <gmd:CI_RoleCode codeList="http://standards.iso.org/ittf/PubliclyAvailableStandards/ISO_19139_Schemas/resources/codelist/ML_gmxCodelists.xml#CI_RoleCode" codeListValue="originator" codeSpace="ISOTC211/19115"/>
                        </gmd:role>
                      </gmd:CI_ResponsibleParty>
                    </gmd:citedResponsibleParty>
                    <gmd:citedResponsibleParty>
                      <gmd:CI_ResponsibleParty>
                        <gmd:organisationName>
                          <gco:CharacterString xmlns:gco="http://www.isotc211.org/2005/gco">National Ocean Service (NOS)</gco:CharacterString>
                        </gmd:organisationName>
                        <gmd:role>
                          <gmd:CI_RoleCode codeList="http://standards.iso.org/ittf/PubliclyAvailableStandards/ISO_19139_Schemas/resources/codelist/ML_gmxCodelists.xml#CI_RoleCode" codeListValue="originator" codeSpace="ISOTC211/19115"/>
                        </gmd:role>
                      </gmd:CI_ResponsibleParty>
                    </gmd:citedResponsibleParty>
                    <gmd:otherCitationDetails>
                      <gco:CharacterString xmlns:gco="http://www.isotc211.org/2005/gco">Since the original data compilation was completed from the original sources, GNIS accepts data or data changes for consideration from any source, and upon validation by the Board on Geographic Names or the appropriate Federal or state agency, will enter the data into the database. The GNIS has an active data gathering and maintenance program. A web-based data date entry and edit application allows authorized users to submit transaction data directly for validation and entry into the database, where it immediately becomes available to all web services and applications. A test and demonstration site with no connection to production data is available for review, training, and familiarization. Batch files will be accepted in most standard formats. Government agencies at all levels are encouraged to join this program. Other organizations and individuals will be considered on a case basis. For additional information or to request user accounts for entry and edit of production data and web seminar training, contact gnis_manager@usgs.gov.</gco:CharacterString>
                    </gmd:otherCitationDetails>
                  </gmd:CI_Citation>
                </gmd:sourceCitation>
                <gmd:sourceExtent>
                  <gmd:EX_Extent>
                    <gmd:description>
                      <gco:CharacterString xmlns:gco="http://www.isotc211.org/2005/gco">Unknown</gco:CharacterString>
                    </gmd:description>
                    <gmd:temporalElement>
                      <gmd:EX_TemporalExtent>
                        <gmd:extent>
                          <gml:TimePeriod xmlns:gml="http://www.opengis.net/gml" gml:id="d1363648e1408">
                            <gml:beginPosition indeterminatePosition="unknown"/>
                            <gml:endPosition indeterminatePosition="unknown"/>
                          </gml:TimePeriod>
                        </gmd:extent>
                      </gmd:EX_TemporalExtent>
                    </gmd:temporalElement>
                  </gmd:EX_Extent>
                </gmd:sourceExtent>
              </gmd:LI_Source>
            </gmd:source>
            <gmd:source>
              <gmd:LI_Source>
                <gmd:description>
                  <gco:CharacterString xmlns:gco="http://www.isotc211.org/2005/gco">XY locations and attributes</gco:CharacterString>
                </gmd:description>
                <gmd:sourceCitation>
                  <gmd:CI_Citation>
                    <gmd:title>
                      <gco:CharacterString xmlns:gco="http://www.isotc211.org/2005/gco">IL_DECI.zip</gco:CharacterString>
                    </gmd:title>
                    <gmd:date>
                      <gmd:CI_Date>
                        <gmd:date>
                          <gco:Date xmlns:gco="http://www.isotc211.org/2005/gco">2006-07-19</gco:Date>
                        </gmd:date>
                        <gmd:dateType>
                          <gmd:CI_DateTypeCode codeList="http://standards.iso.org/ittf/PubliclyAvailableStandards/ISO_19139_Schemas/resources/codelist/ML_gmxCodelists.xml#CI_DateTypeCode" codeListValue="publication" codeSpace="ISOTC211/19115"/>
                        </gmd:dateType>
                      </gmd:CI_Date>
                    </gmd:date>
                    <gmd:edition>
                      <gco:CharacterString xmlns:gco="http://www.isotc211.org/2005/gco">20060719</gco:CharacterString>
                    </gmd:edition>
                    <gmd:citedResponsibleParty>
                      <gmd:CI_ResponsibleParty>
                        <gmd:organisationName>
                          <gco:CharacterString xmlns:gco="http://www.isotc211.org/2005/gco">US Board on Geographic Names</gco:CharacterString>
                        </gmd:organisationName>
                        <gmd:role>
                          <gmd:CI_RoleCode codeList="http://standards.iso.org/ittf/PubliclyAvailableStandards/ISO_19139_Schemas/resources/codelist/ML_gmxCodelists.xml#CI_RoleCode" codeListValue="originator" codeSpace="ISOTC211/19115"/>
                        </gmd:role>
                      </gmd:CI_ResponsibleParty>
                    </gmd:citedResponsibleParty>
                    <gmd:presentationForm>
                      <gmd:CI_PresentationFormCode codeList="http://standards.iso.org/ittf/PubliclyAvailableStandards/ISO_19139_Schemas/resources/codelist/ML_gmxCodelists.xml#CI_PresentationFormCode" codeListValue="documentDigital" codeSpace="ISOTC211/19115"/>
                    </gmd:presentationForm>
                    <gmd:otherCitationDetails>
                      <gco:CharacterString xmlns:gco="http://www.isotc211.org/2005/gco">The Illinois data file was downloaded on 20060823.</gco:CharacterString>
                    </gmd:otherCitationDetails>
                  </gmd:CI_Citation>
                </gmd:sourceCitation>
                <gmd:sourceExtent>
                  <gmd:EX_Extent>
                    <gmd:description>
                      <gco:CharacterString xmlns:gco="http://www.isotc211.org/2005/gco">publication date</gco:CharacterString>
                    </gmd:description>
                    <gmd:temporalElement>
                      <gmd:EX_TemporalExtent>
                        <gmd:extent>
                          <gml:TimePeriod xmlns:gml="http://www.opengis.net/gml" gml:id="d1363648e1484">
                            <gml:beginPosition>1974-01-01</gml:beginPosition>
                            <gml:endPosition>2006-07-19</gml:endPosition>
                          </gml:TimePeriod>
                        </gmd:extent>
                      </gmd:EX_TemporalExtent>
                    </gmd:temporalElement>
                  </gmd:EX_Extent>
                </gmd:sourceExtent>
              </gmd:LI_Source>
            </gmd:source>
            <gmd:source>
              <gmd:LI_Source>
                <gmd:description>
                  <gco:CharacterString xmlns:gco="http://www.isotc211.org/2005/gco">Feature names and attribute information</gco:CharacterString>
                </gmd:description>
                <gmd:sourceCitation>
                  <gmd:CI_Citation>
                    <gmd:title>
                      <gco:CharacterString xmlns:gco="http://www.isotc211.org/2005/gco">Records of the U.S. Board on Geographic Names</gco:CharacterString>
                    </gmd:title>
                    <gmd:alternateTitle>
                      <gco:CharacterString xmlns:gco="http://www.isotc211.org/2005/gco">USBGN</gco:CharacterString>
                    </gmd:alternateTitle>
                    <gmd:citedResponsibleParty>
                      <gmd:CI_ResponsibleParty>
                        <gmd:organisationName>
                          <gco:CharacterString xmlns:gco="http://www.isotc211.org/2005/gco">U.S. Geological Survey</gco:CharacterString>
                        </gmd:organisationName>
                        <gmd:role>
                          <gmd:CI_RoleCode codeList="http://standards.iso.org/ittf/PubliclyAvailableStandards/ISO_19139_Schemas/resources/codelist/ML_gmxCodelists.xml#CI_RoleCode" codeListValue="originator" codeSpace="ISOTC211/19115"/>
                        </gmd:role>
                      </gmd:CI_ResponsibleParty>
                    </gmd:citedResponsibleParty>
                  </gmd:CI_Citation>
                </gmd:sourceCitation>
                <gmd:sourceExtent>
                  <gmd:EX_Extent>
                    <gmd:description>
                      <gco:CharacterString xmlns:gco="http://www.isotc211.org/2005/gco">Creation date</gco:CharacterString>
                    </gmd:description>
                    <gmd:temporalElement>
                      <gmd:EX_TemporalExtent>
                        <gmd:extent>
                          <gml:TimePeriod xmlns:gml="http://www.opengis.net/gml" gml:id="d1363648e1545">
                            <gml:beginPosition>1890-01-01</gml:beginPosition>
                            <gml:endPosition indeterminatePosition="now"/>
                          </gml:TimePeriod>
                        </gmd:extent>
                      </gmd:EX_TemporalExtent>
                    </gmd:temporalElement>
                  </gmd:EX_Extent>
                </gmd:sourceExtent>
              </gmd:LI_Source>
            </gmd:source>
            <gmd:source>
              <gmd:LI_Source>
                <gmd:description>
                  <gco:CharacterString xmlns:gco="http://www.isotc211.org/2005/gco">Feature names and attribute data.</gco:CharacterString>
                </gmd:description>
                <gmd:scaleDenominator>
                  <gmd:MD_RepresentativeFraction>
                    <gmd:denominator>
                      <gco:Integer xmlns:gco="http://www.isotc211.org/2005/gco">24000</gco:Integer>
                    </gmd:denominator>
                  </gmd:MD_RepresentativeFraction>
                </gmd:scaleDenominator>
                <gmd:sourceCitation>
                  <gmd:CI_Citation>
                    <gmd:title>
                      <gco:CharacterString xmlns:gco="http://www.isotc211.org/2005/gco">1:24,000-scale topographic maps</gco:CharacterString>
                    </gmd:title>
                    <gmd:alternateTitle>
                      <gco:CharacterString xmlns:gco="http://www.isotc211.org/2005/gco">USGS</gco:CharacterString>
                    </gmd:alternateTitle>
                    <gmd:citedResponsibleParty>
                      <gmd:CI_ResponsibleParty>
                        <gmd:organisationName>
                          <gco:CharacterString xmlns:gco="http://www.isotc211.org/2005/gco">U.S. Geological Survey</gco:CharacterString>
                        </gmd:organisationName>
                        <gmd:contactInfo>
                          <gmd:CI_Contact>
                            <gmd:address>
                              <gmd:CI_Address>
                                <gmd:deliveryPoint>
                                  <gco:CharacterString xmlns:gco="http://www.isotc211.org/2005/gco">Reston, VA</gco:CharacterString>
                                </gmd:deliveryPoint>
                              </gmd:CI_Address>
                            </gmd:address>
                          </gmd:CI_Contact>
                        </gmd:contactInfo>
                        <gmd:role>
                          <gmd:CI_RoleCode codeList="http://standards.iso.org/ittf/PubliclyAvailableStandards/ISO_19139_Schemas/resources/codelist/ML_gmxCodelists.xml#CI_RoleCode" codeListValue="publisher" codeSpace="ISOTC211/19115"/>
                        </gmd:role>
                      </gmd:CI_ResponsibleParty>
                    </gmd:citedResponsibleParty>
                    <gmd:citedResponsibleParty>
                      <gmd:CI_ResponsibleParty>
                        <gmd:organisationName>
                          <gco:CharacterString xmlns:gco="http://www.isotc211.org/2005/gco">U.S. Geological Survey</gco:CharacterString>
                        </gmd:organisationName>
                        <gmd:role>
                          <gmd:CI_RoleCode codeList="http://standards.iso.org/ittf/PubliclyAvailableStandards/ISO_19139_Schemas/resources/codelist/ML_gmxCodelists.xml#CI_RoleCode" codeListValue="originator" codeSpace="ISOTC211/19115"/>
                        </gmd:role>
                      </gmd:CI_ResponsibleParty>
                    </gmd:citedResponsibleParty>
                    <gmd:presentationForm>
                      <gmd:CI_PresentationFormCode codeList="http://standards.iso.org/ittf/PubliclyAvailableStandards/ISO_19139_Schemas/resources/codelist/ML_gmxCodelists.xml#CI_PresentationFormCode" codeListValue="mapHardcopy" codeSpace="ISOTC211/19115"/>
                    </gmd:presentationForm>
                  </gmd:CI_Citation>
                </gmd:sourceCitation>
                <gmd:sourceExtent>
                  <gmd:EX_Extent>
                    <gmd:description>
                      <gco:CharacterString xmlns:gco="http://www.isotc211.org/2005/gco">publication date</gco:CharacterString>
                    </gmd:description>
                    <gmd:temporalElement>
                      <gmd:EX_TemporalExtent>
                        <gmd:extent>
                          <gml:TimePeriod xmlns:gml="http://www.opengis.net/gml" gml:id="d1363648e1645">
                            <gml:beginPosition indeterminatePosition="unknown"/>
                            <gml:endPosition indeterminatePosition="now"/>
                          </gml:TimePeriod>
                        </gmd:extent>
                      </gmd:EX_TemporalExtent>
                    </gmd:temporalElement>
                  </gmd:EX_Extent>
                </gmd:sourceExtent>
              </gmd:LI_Source>
            </gmd:source>
            <gmd:source>
              <gmd:LI_Source>
                <gmd:description>
                  <gco:CharacterString xmlns:gco="http://www.isotc211.org/2005/gco">Feature names and attribute information</gco:CharacterString>
                </gmd:description>
                <gmd:sourceCitation>
                  <gmd:CI_Citation>
                    <gmd:title>
                      <gco:CharacterString xmlns:gco="http://www.isotc211.org/2005/gco">National Ocean Service charts</gco:CharacterString>
                    </gmd:title>
                    <gmd:alternateTitle>
                      <gco:CharacterString xmlns:gco="http://www.isotc211.org/2005/gco">NOAA/NOS</gco:CharacterString>
                    </gmd:alternateTitle>
                    <gmd:citedResponsibleParty>
                      <gmd:CI_ResponsibleParty>
                        <gmd:organisationName>
                          <gco:CharacterString xmlns:gco="http://www.isotc211.org/2005/gco">National Ocean Service (NOS)</gco:CharacterString>
                        </gmd:organisationName>
                        <gmd:role>
                          <gmd:CI_RoleCode codeList="http://standards.iso.org/ittf/PubliclyAvailableStandards/ISO_19139_Schemas/resources/codelist/ML_gmxCodelists.xml#CI_RoleCode" codeListValue="originator" codeSpace="ISOTC211/19115"/>
                        </gmd:role>
                      </gmd:CI_ResponsibleParty>
                    </gmd:citedResponsibleParty>
                  </gmd:CI_Citation>
                </gmd:sourceCitation>
                <gmd:sourceExtent>
                  <gmd:EX_Extent>
                    <gmd:description>
                      <gco:CharacterString xmlns:gco="http://www.isotc211.org/2005/gco">Publication date</gco:CharacterString>
                    </gmd:description>
                    <gmd:temporalElement>
                      <gmd:EX_TemporalExtent>
                        <gmd:extent>
                          <gml:TimePeriod xmlns:gml="http://www.opengis.net/gml" gml:id="d1363648e1704">
                            <gml:beginPosition indeterminatePosition="unknown"/>
                            <gml:endPosition indeterminatePosition="now"/>
                          </gml:TimePeriod>
                        </gmd:extent>
                      </gmd:EX_TemporalExtent>
                    </gmd:temporalElement>
                  </gmd:EX_Extent>
                </gmd:sourceExtent>
              </gmd:LI_Source>
            </gmd:source>
          </gmd:LI_Lineage>
        </gmd:lineage>
      </gmd:DQ_DataQuality>
    </gmd:dataQualityInfo>
    <gmd:metadataConstraints>
      <gmd:MD_Constraints>
        <gmd:useLimitation>
          <gco:CharacterString xmlns:gco="http://www.isotc211.org/2005/gco">The use constraints as stated for the data apply also to the metadata. Refer to the Use Constraints section of the Identification Information section.</gco:CharacterString>
        </gmd:useLimitation>
      </gmd:MD_Constraints>
    </gmd:metadataConstraints>
    <gmd:metadataConstraints>
      <gmd:MD_LegalConstraints>
        <gmd:accessConstraints>
          <gmd:MD_RestrictionCode codeList="http://standards.iso.org/ittf/PubliclyAvailableStandards/ISO_19139_Schemas/resources/codelist/ML_gmxCodelists.xml#MD_RestrictionCode" codeListValue="otherRestrictions" codeSpace="ISOTC211/19115"/>
        </gmd:accessConstraints>
        <gmd:otherConstraints>
          <gco:CharacterString xmlns:gco="http://www.isotc211.org/2005/gco">The access constraints as stated for the data apply also to the metadata. Refer to the Access Constraints section of the Identification Information section.</gco:CharacterString>
        </gmd:otherConstraints>
      </gmd:MD_LegalConstraints>
    </gmd:metadataConstraints>
    <gmd:metadataMaintenance>
      <gmd:MD_MaintenanceInformation>
        <gmd:maintenanceAndUpdateFrequency>
          <gmd:MD_MaintenanceFrequencyCode codeList="http://standards.iso.org/ittf/PubliclyAvailableStandards/ISO_19139_Schemas/resources/codelist/ML_gmxCodelists.xml#MD_MaintenanceFrequencyCode" codeListValue="asNeeded" codeSpace="ISOTC211/19115"/>
        </gmd:maintenanceAndUpdateFrequency>
        <gmd:maintenanceNote>
          <gco:CharacterString xmlns:gco="http://www.isotc211.org/2005/gco">Metadata was translated into ISO 19139 for inclusion in the Big Ten Academic Alliance Geospatial Data Project.</gco:CharacterString>
        </gmd:maintenanceNote>
        <gmd:contact>
          <gmd:CI_ResponsibleParty>
            <gmd:individualName>
              <gco:CharacterString xmlns:gco="http://www.isotc211.org/2005/gco">James V. Whitacre</gco:CharacterString>
            </gmd:individualName>
            <gmd:organisationName>
              <gco:CharacterString xmlns:gco="http://www.isotc211.org/2005/gco">University of Illinois at Urbana-Champaign, Library</gco:CharacterString>
            </gmd:organisationName>
            <gmd:positionName>
              <gco:CharacterString xmlns:gco="http://www.isotc211.org/2005/gco">GIS Specialist</gco:CharacterString>
            </gmd:positionName>
            <gmd:contactInfo>
              <gmd:CI_Contact>
                <gmd:address>
                  <gmd:CI_Address>
                    <gmd:country>
                      <gco:CharacterString xmlns:gco="http://www.isotc211.org/2005/gco">US</gco:CharacterString>
                    </gmd:country>
                    <gmd:electronicMailAddress>
                      <gco:CharacterString xmlns:gco="http://www.isotc211.org/2005/gco">jvwhit@illinois.edu</gco:CharacterString>
                    </gmd:electronicMailAddress>
                  </gmd:CI_Address>
                </gmd:address>
              </gmd:CI_Contact>
            </gmd:contactInfo>
            <gmd:role>
              <gmd:CI_RoleCode codeList="http://standards.iso.org/ittf/PubliclyAvailableStandards/ISO_19139_Schemas/resources/codelist/ML_gmxCodelists.xml#CI_RoleCode" codeListValue="pointOfContact" codeSpace="ISOTC211/19115"/>
            </gmd:role>
          </gmd:CI_ResponsibleParty>
        </gmd:contact>
        <gmd:updateScopeDescription>
          <gmd:MD_ScopeDescription>
            <gmd:other>
              <gco:CharacterString xmlns:gco="http://www.isotc211.org/2005/gco">Illinois</gco:CharacterString>
            </gmd:other>
          </gmd:MD_ScopeDescription>
        </gmd:updateScopeDescription>
      </gmd:MD_MaintenanceInformation>
    </gmd:metadataMaintenance>
  </gmd:MD_Metadata>
  