{
  "dc_identifier_s": "05c80d49-922f-47f2-be8f-64d04e601c51",
  "dc_title_s": "Stream Sections that Support Wild Trout Production: Pennsylvania",
  "dc_description_s": "This layer contains flowing waters in Pennsylvania that support naturally reproducing populations of trout. A wild trout stream section is a biological designation that does not determine how it is managed, therefore, these streams may also be stocked with hatchery trout by the Commission. This GIS layer matches the list available on the PFBC web site at http://www.fish.state.pa.us/trout_repro.htm.",
  "dc_rights_s": "Public",
  "dc_format_s": "Files",
  "dc_language_sm": [
    "English"
  ],
  "dc_type_sm": "Dataset",
  "dc_publisher_sm": [
    "Pennsylvania Fish and Boat Commission"
  ],
  "dc_creator_sm": [
    "Pennsylvania Fish and Boat Commission"
  ],
  "dc_subject_sm": [
    "Biota",
    "Recreation"
  ],
  "dct_provenance_s": "Penn State",
  "dct_references_s": "{\"http://schema.org/url\":\"http://www.pasda.psu.edu/uci/DataSummary.aspx?dataset=980\",\"http://schema.org/downloadUrl\":\"http://www.pasda.psu.edu/uci/DataSummary.aspx?dataset=980\"}",
  "dct_isPartOf_sm": [
    "Pennsylvania Spatial Data Access (PASDA)"
  ],
  "dct_issued_s": "",
  "dct_temporal_sm": [
    "2017"
  ],
  "dct_spatial_sm": [
    "Pennsylvania, United States"
  ],
  "layer_slug_s": "05c80d49-922f-47f2-be8f-64d04e601c51",
  "layer_geom_type_s": "Vector",
  "layer_modified_dt": "2018-06-26T21:06:44Z",
  "solr_geom": "ENVELOPE(-74.777238, -80.315469, 42.048595, 39.720295)",
  "solr_year_i": 2017,
  "b1g_genre_sm": [
    "Geospatial data"
  ],
  "b1g_centroid_ss": "40.884445,-77.5463535",
  "b1g_geonames_sm": [
    "http://sws.geonames.org/6254927"
  ],
  "b1g_image_ss": "",
  "b1g_collection_sm": "08a-01",
  "geoblacklight_version": "1.0"
}