{
  "dc_identifier_s": "423f8e0cd726488abaf1f329f834b55d_0",
  "dc_title_s": "Truck Routes: Southeast Michigan",
  "dc_description_s": "This feature class contains Michigan Geographic Framework v.10 roads that are designed for heavy truck travel in Southeast Michigan. These roads are either all-season (higher weight limits during seasonal load limit periods) State roads, all-season County roads, or intermodal connectors. This feature class does not contain city roads. This feature class does not contain roads with heavy truck traffic that have seasonal load limits.",
  "dc_rights_s": "Public",
  "dc_format_s": "Shapefile",
  "dc_language_sm": [
    "English"
  ],
  "dc_type_sm": [
    "Dataset",
    "Service"
  ],
  "dc_publisher_sm": [
    "SEMCOG, Southeast Michigan Council of Governments"
  ],
  "dc_creator_sm": [
    "SEMCOG, Southeast Michigan Council of Governments"
  ],
  "dc_subject_sm": [
    "Transportation"
  ],
  "dct_provenance_s": "Michigan State",
  "dct_references_s": "{\"http://schema.org/downloadUrl\":\"https://maps-semcog.opendata.arcgis.com/datasets/423f8e0cd726488abaf1f329f834b55d_0\",\"http://schema.org/downloadUrl\":\"https://data.imap.maryland.gov/datasets/2cb6e7dfc87047ccaa38f59d955d907b_2,\"urn:x-esri:serviceType:ArcGIS#DynamicMapLayer\":\"https://maps-semcog.opendata.arcgis.com/datasets/423f8e0cd726488abaf1f329f834b55d_0\"}",
  "dct_isPartOf_sm": [
    "ArcGIS Open Data"
  ],
  "dct_issued_s": "2015",
  "dct_temporal_sm": [

  ],
  "dct_spatial_sm": [
    "Michigan, United States"
  ],
  "layer_slug_s": "423f8e0cd726488abaf1f329f834b55d_0",
  "layer_geom_type_s": "Vector",
  "layer_modified_dt": "2018-07-10T14:46:07Z",
  "solr_geom": "ENVELOPE(-84.152493, -82.418153, 43.183703, 41.709774)",
  "solr_year_i": 2015,
  "b1g_genre_sm": [
    "Geospatial data"
  ],
  "b1g_geom_type_sm": [
    "Vector data"
  ],
  "b1g_centroid_ss": "42.4467385,-83.285323",
  "b1g_geonames_sm": [

  ],
  "b1g_image_ss": "",
  "b1g_collection_sm": "ArcGIS Open Data",
  "geoblacklight_version": "1.0"
}