{
  "dc_identifier_s": "b6d23218-c5be-493b-a02c-6234017d67c3",
  "dc_title_s": "The 1899-1900 famine map of the Presidency of Bombay, showing the divisions of collectorates, talukas and principal native state",
  "dc_description_s": "1294 x 789 mm",
  "dc_rights_s": "Public",
  "dc_format_s": "TIFF",
  "dc_language_sm": [
    "English"
  ],
  "dc_type_sm": [
    "Image"
  ],
  "dc_publisher_sm": [
    "Govt. Photozinco Office"
  ],
  "dc_creator_sm": [

  ],
  "dc_subject_sm": [
    "Famines"
  ],
  "dct_provenance_s": "Minnesota",
  "dct_references_s": "{\"http://schema.org/url\":\"http://purl.umn.edu/225724\",\"http://schema.org/downloadUrl\":\"https://umedia.lib.umn.edu/sites/default/files/archive/562/image/tiff/1084445.tif\",\"http://iiif.io/api/image\":\"https://umedia.lib.umn.edu/fcgi-bin/iipsrv.fcgi?IIIF=sites/default/files/reference/562/image/jp2/1084445.jp2/info.json\"}",
  "dct_isPartOf_sm": [
    "John R. Borchert Map Library"
  ],
  "dct_issued_s": "",
  "dct_temporal_sm": [
    "1901"
  ],
  "dct_spatial_sm": [
    "India"
  ],
  "layer_slug_s": "b6d23218-c5be-493b-a02c-6234017d67c3",
  "layer_geom_type_s": "Image",
  "layer_modified_dt": "2018-07-06T18:49:51Z",
  "solr_geom": "ENVELOPE(67, 76.83, 28.83, 14)",
  "solr_year_i": 1901,
  "b1g_genre_sm": [
    "Maps"
  ],
  "b1g_centroid_ss": "21.415,71.915",
  "b1g_geonames_sm": [
    "http://sws.geonames.org/1269750"
  ],
  "b1g_image_ss": "https://umedia.lib.umn.edu/sites/default/files/imagecache/square300/reference/562/image/jpeg/1084445.jpg",
  "b1g_collection_sm": "05d-01",
  "geoblacklight_version": "1.0"
}