{
  "dc_identifier_s": "d87a05ee-899f-4e01-a8b3-57a20d54a206",
  "dc_title_s": "WPC non-protected sites: Western Pennsylvania",
  "dc_description_s": "Final export of all aquatic sampling sites from the Pennsylvania Aquatic Database (PAD) at the completion of Phase I of the Pennsylvania Aquatic Community Classification project that had no datarelease restrictions (approximately 14% of all stations). This project was undertaken by the Pennsylvania Natural Heritage Program.",
  "dc_rights_s": "Public",
  "dc_format_s": "Files",
  "dc_language_sm": [
    "English"
  ],
  "dc_type_sm": "Dataset",
  "dc_publisher_sm": [
    "Western Pennsylvania Conservancy"
  ],
  "dc_creator_sm": [
    "Pennsylvania Natural Heritage Program"
  ],
  "dc_subject_sm": [
    "Inland Waters",
    "Hydrology"
  ],
  "dct_provenance_s": "Penn State",
  "dct_references_s": "{\"http://schema.org/url\":\"http://www.pasda.psu.edu/uci/DataSummary.aspx?dataset=1445\",\"http://schema.org/downloadUrl\":\"http://www.pasda.psu.edu/uci/DataSummary.aspx?dataset=1445\"}",
  "dct_isPartOf_sm": [
    "Pennsylvania Spatial Data Access (PASDA)"
  ],
  "dct_issued_s": "",
  "dct_temporal_sm": [
    "2004"
  ],
  "dct_spatial_sm": [
    "Pennsylvania, United States"
  ],
  "layer_slug_s": "d87a05ee-899f-4e01-a8b3-57a20d54a206",
  "layer_geom_type_s": "Vector",
  "layer_modified_dt": "2018-06-26T21:06:44Z",
  "solr_geom": "ENVELOPE(-74.2589, -83.55566, 42.85103, 35.58029)",
  "solr_year_i": 2004,
  "b1g_genre_sm": [
    "Geospatial data"
  ],
  "b1g_centroid_ss": "39.21566,-78.90728",
  "b1g_geonames_sm": [
    "http://sws.geonames.org/6254927"
  ],
  "b1g_image_ss": "",
  "b1g_collection_sm": "08a-01",
  "geoblacklight_version": "1.0"
}