{
  "uuid": "f7cd3e27-d653-4373-bece-2b79517a5fad",
  "dc_identifier_s": "f7cd3e27-d653-4373-bece-2b79517a5fad",
  "dc_title_s": "Political & Time Chart - Northern Hemisphere Version 2 (1947) Region: Arctic Area: Northern Hemisphere",
  "dc_description_s": "Part of the series: Aeronautical Chart Service Thematic Charts; Scale =1 : 24,000,000. All maps are copyright of their respective owners. By downloading and using the map, you are subject to the map's copyright terms and agree to the PGC's Acknowledgement Policy: https://www.pgc.umn.edu/guides/user-services/acknowledgement-policy/. This map was obtained from the Byrd Polar Research Center at The Ohio State University and the digital version is hosted by the Polar Geospatial Center at the University of Minnesota.",
  "dc_rights_s": "Public",
  "dc_format_s": "GeoTIFF",
  "dc_language_s": [
    "English"
  ],
  "dc_type_s": "Image",
  "dc_publisher_sm": [
    "National Geospatial-Intelligence Agency"
  ],
  "dc_creator_sm": [

  ],
  "dc_subject_sm": [
    "Imagery and Base Maps"
  ],
  "dct_provenance_s": "Ohio",
  "dct_references_s": "{\"http://schema.org/url\":\"http://maps.apps.pgc.umn.edu/id/1218\",\"http://schema.org/downloadUrl\":\"http://data.pgc.umn.edu/maps/arctic/nga/15/geo/Northern%20Hemisphere%20Political%20and%20Time.zip\"}",
  "dct_isPartOf_sm": "Byrd Polar Research Center",
  "dct_issued_s": [

  ],
  "dct_temporal_sm": [
    "1947"
  ],
  "dct_spatial_sm": [
    "Arctic"
  ],
  "b1g_geonames_sm": [
    "http://sws.geonames.org/10941926"
  ],
  "thumbnail_path_ss": "http://data.pgc.umn.edu/maps/arctic/nga/15/geo/Northern%20Hemisphere%20Political%20and%20Time.zip",
  "layer_slug_s": "f7cd3e27-d653-4373-bece-2b79517a5fad",
  "layer_geom_type_s": "Scanned Map",
  "layer_modified_dt": "2018-3-2T17:38:48Z",
  "centroid_s": "67.955,0",
  "solr_geom": "ENVELOPE(-180.0, 180.0, 84.71, 51.2)",
  "solr_year_i": 1947
}