{
  "uuid": "dab35a93-0762-4d33-83f6-5cfaaef548f2",
  "dc_identifier_s": "dab35a93-0762-4d33-83f6-5cfaaef548f2",
  "dc_title_s": "Chicago Park District Artworks: Chicago, Illinois",
  "dc_description_s": "Inventory of public art located on Chicago Park District premises as of November 4, 2016.",
  "dc_rights_s": "Public",
  "dc_format_s": "Shapefile",
  "dc_language_s": [

  ],
  "dc_type_s": "Dataset",
  "dc_publisher_sm": [
    "City of Chicago, Illinois"
  ],
  "dc_creator_sm": "City of Chicago",
  "dc_subject_sm": [
    "Society"
  ],
  "dct_provenance_s": "Illinois",
  "dct_references_s": "{\"http://schema.org/url\":\"https://data.cityofchicago.org/d/e9ef-hrzb\",\"http://schema.org/downloadUrl\":\"https://data.cityofchicago.org/api/geospatial/e9ef-hrzb?method=export&format=Original\"}",
  "dct_isPartOf_sm": "City of Chicago Data Portal",
  "dct_issued_s": "2015-03-19",
  "dct_temporal_sm": [
    "2015"
  ],
  "dct_spatial_sm": [
    "Chicago, Illinois, United States"
  ],
  "dc_relation_sm": [
    "http://sws.geonames.org/4887398"
  ],
  "layer_slug_s": "dab35a93-0762-4d33-83f6-5cfaaef548f2",
  "layer_geom_type_s": "Point",
  "layer_modified_dt": "2018-3-19T19:12:57Z",
  "centroid_s": "41.842661,-87.6739935",
  "solr_geom": "ENVELOPE(-87.9402669, -87.523661, 42.023220, 41.6443349)",
  "solr_year_i": 2015
}